Workbook

Sheet Abilities
A1: =COUNTIF(A2:A1999,"=0") -> 458 | E1: This column is for developing the actual game text of an ability
B2: Category | C2: Ability Name | D2: Ability Description | E2: Rules Text | F2: BP Cost | G2: Affinity req | H2: W | I2: U | J2: B | K2: R | L2: G | M2: tot | O2: R1 | P2: R2 | Q2: R3 | R2: R4 | S2: R5 | T2: R6 | U2: R7 | V2: R8 | W2: R9 | X2: R10
A3: =ISBLANK(B3)+ISBLANK(C3)+ISBLANK(D3)+ISBLANK(E3)+ISBLANK(F3)+ISBLANK(G3) -> 0 | B3: Aura | C3: Drinker of Souls | D3: Automatically absorb energy from dying / recently slain foes | E3: A creature that begins dying or loses health while dying within the aura rolls BOD vs. WIL to resist, failure or tie results in its death. This aura automatically succeeds against a target that has been dead for up to 5 rounds, on 6+ rounds no effect. When a creature's soul is consumed gain 1 temporary HP, stacking. A creature's soul can only be so consumed once. If multiple instances of this ability would trigger on a soul, the owner who most recently acted in initiative gets priority, then second most recent, etc. | F3: 10 | G3: 7B,(9) | H3: 0 | I3: 0 | J3: 6 | K3: 0 | L3: 0 | M3: 6 | O3: 10 | Y3: Drinker of souls generates stacking temp health and provides a culling effect. The value of the culling effect remains to be seen as enemies healing downed allies seems a lot rarer than it should be? Stackable THP feels like something for the middle bracket (TR 4-6, maybe 7). How does it piggyback on other THP generation? Given it takes up the aura slot, this ability can likely preserve its low cost. Though it should probably be limited at the very least +20 Generates 1 THP -10 On kill trigger (any ally or you), no action +40? stacking THP -20 aura discount new price: 30
A4: =ISBLANK(B4)+ISBLANK(C4)+ISBLANK(D4)+ISBLANK(E4)+ISBLANK(F4)+ISBLANK(G4) -> 0 | B4: Aura | C4: Enduring Presence | D4: Damage dampening, discharge to mitigate one hit | E4: Allies within the aura gain RANK+1 damage dampening. Discharge: one subject of the aura gets RANK+1+(quantity of subjects) damage dampening against one attack. | F4: 60/70/80 | G4: 12W,(15) 16W,(21) 20W,(27) | H4: 6 | M4: 6 | O4: 60 | P4: 130 | Q4: 210 | Y4: Big white defensive aura. Doesn't feel out of place on any details at this point 200/300/400 provides Rank+1 dampening 2x Provides benefits to party -20 aura discount discharge function 0.2x Complex, prepared in advance 500/600/700 dampening
A5: =ISBLANK(B5)+ISBLANK(C5)+ISBLANK(D5)+ISBLANK(E5)+ISBLANK(F5)+ISBLANK(G5) -> 0 | B5: Aura | C5: Fear Aura | D5: This fear aura triggers on any aggressive action. | E5: You may attempt a free intimidation check against all enemies within the aura once per round as part of an attack. The effects of the intimidation check apply after the attack is resolved. As normal, you can only apply one fear effect to a given target once per turn. | F5: 15 | G5: 4R,5(B|R),(12) | H5: 0 | I5: 0 | J5: 6 | K5: 6 | L5: 0 | M5: 6 | O5: 15 | Y5: Fear is supposedly a B|R effect. So perhaps exclusive B|R? TR4-6. Price can stay low given it triggers infrequently. It's otherwise a potent effect, but it is an aura.
A6: =ISBLANK(B6)+ISBLANK(C6)+ISBLANK(D6)+ISBLANK(E6)+ISBLANK(F6)+ISBLANK(G6) -> 0 | B6: Aura | C6: Feedback Aura | D6: Nearby enemies subject to damage when you are wounded | E6: Enemies in the aura (CHA/2 *5 ft instead of standard CHA*5) resist (damage you took+CHA-2) as psychic damage with mental soak. | F6: 10 | G6: 4(W|B),4(W|U|B),(15) | H6: 0 | I6: 4 | J6: 4 | K6: 0 | L6: 0 | M6: 8 | O6: 10 | Y6: Defense bypassing thorns effect. Feels to be more of a W|B effect. Good for popping mooks. Has obvious synergy with THP
A7: =ISBLANK(B7)+ISBLANK(C7)+ISBLANK(D7)+ISBLANK(E7)+ISBLANK(F7)+ISBLANK(G7) -> 0 | B7: Aura | C7: Generous Enchancements | D7: Share the effects of one ongoing buff you are subject to with all allies in range of this aura. | E7: When you trigger a buff you may designate it as being Generously Enhanced. This ability becomes the shared aura effect of Generous Enhancements and does not count for you as a body buff if it was one. As a Extra action you may designate a buff currently on you to become Generously Enhanced, it becomes the aura effect and any current aura effect reverts to its normal buff state. | F7: 100 | G7: 12W,12G,(30) | O7: 100
A8: =ISBLANK(B8)+ISBLANK(C8)+ISBLANK(D8)+ISBLANK(E8)+ISBLANK(F8)+ISBLANK(G8) -> 0 | B8: Aura | C8: Glare of the noonday sun | D8: nonlethal damage vs. everything at start of your turn | E8: All creatures within (CHA/2 + RANK) ft (including you) must soak (BOD + 2* RANK) fire damage at the start of your turn. This damage is always nonlethal. | F8: 30/40/50 | G8: 14(W|R|G),(18) 16(W|R|G),(21) 19(W|R|G),(24) | H8: 12 | K8: 12 | L8: 12 | M8: 12 | O8: 30 | P8: 70 | Q8: 120 | Y8: tri color exclusive, accessible to 3x 2c, matching 3c, and 6 (2/3) match 3c that stretch. Culls mooks generally
A9: =ISBLANK(B9)+ISBLANK(C9)+ISBLANK(D9)+ISBLANK(E9)+ISBLANK(F9)+ISBLANK(G9) -> 0 | B9: Aura | C9: Lawbringer's Presence | D9: Free counterspell attempts on any spells cast within this aura | E9: You may attempt to counterspell any spell cast within this aura for (0) | F9: 100 | G9: 8W,8U,8(W|U),(30) | O9: 100 | Y9: Should all capstones be partial color flex?
A10: =ISBLANK(B10)+ISBLANK(C10)+ISBLANK(D10)+ISBLANK(E10)+ISBLANK(F10)+ISBLANK(G10) -> 0 | B10: Aura | C10: Magic Circle of Heart | D10: All allies in the aura gain rank X to an element of your choice, chosen on activation. | E10: All allies in the aura gain 2*RANK resist to ELEMENT of your choice, chosen on activation. | F10: 20,30,40 | G10: 3W,(9) per | O10: 20 | P10: 50 | Q10: 90 | Y10: May be a bit underpriced for how potent it could be? Green magic resist seems to be another theme that could be called upon
A11: =ISBLANK(B11)+ISBLANK(C11)+ISBLANK(D11)+ISBLANK(E11)+ISBLANK(F11)+ISBLANK(G11) -> 0 | B11: Aura | C11: Mana Leech | D11: Name a color. All drain using abilities except for the named color are subject to 1 higher drain. Whenever such an ability is used, roll 4 dice and heal HITS drain. | E11: Name a color on aura activation. All spells and other drain using abilities used within the aura except for the named color may take 2+2*RANK overload. If they don't, roll 2+2*rank dice and heal HITS drain and the ability user loses HITS drain. | F11: 20,30,40 | G11: 7U,7B,(18) 9U,9B,(24) 12U,12B,(30) | H11: 10 | J11: 10 | M11: 10 | O11: 20 | P11: 50 | Q11: 90 | Y11: Spells only. May be slighly underpriced?
A12: =ISBLANK(B12)+ISBLANK(C12)+ISBLANK(D12)+ISBLANK(E12)+ISBLANK(F12)+ISBLANK(G12) -> 0 | B12: Aura | C12: Menacing Presence | D12: Penalty to enemies trying to attack allies other than you | E12: Enemies within (CHA*5 feet) take (CHA) penalty to their attack pools if targeting anything but a user of Menacing Presence. If enemies are not aware of you, this aura does not affect them. | F12: 10 | G12: 4W,5(W|B|G),(12) | H12: 6 | I12: 0 | J12: 6 | K12: 0 | L12: 0 | M12: 6 | O12: 10
A13: =ISBLANK(B13)+ISBLANK(C13)+ISBLANK(D13)+ISBLANK(E13)+ISBLANK(F13)+ISBLANK(G13) -> 0 | B13: Aura | C13: Natural Shielding | D13: Aura, allies gain resistances | E13: All allies within the aura gain +RANK armor, and 2*RANK+2 dice on rolls to resist effects originating from other recipients of this aura. | F13: 40/50/60 | G13: 7G,(15) 10G,(21) 13G,(27) | L13: 4 | M13: 10 | O13: 40 | P13: 90 | Q13: 150
A14: =ISBLANK(B14)+ISBLANK(C14)+ISBLANK(D14)+ISBLANK(E14)+ISBLANK(F14)+ISBLANK(G14) -> 0 | B14: Aura | C14: Never surrender | D14: grants diehard to allies | E14: Allies do not fall unconscious when a damage track is filled. They still die from overflow. | F14: 10 | G14: 6W,6R,(15) | H14: 8 | I14: 0 | J14: 0 | K14: 8 | L14: 0 | M14: 8 | O14: 10
A15: =ISBLANK(B15)+ISBLANK(C15)+ISBLANK(D15)+ISBLANK(E15)+ISBLANK(F15)+ISBLANK(G15) -> 0 | B15: Aura | C15: No Retreat! | D15: Your inspiration prevents enemies from being able to withdraw safely | E15: Enemies within your zone of control provoke attacks of opportunity from you when using any form of movement even if they would not normally provoke. At rank 2 all enemies within CHA*5 always provoke attacks of opportunity (from threatening allies) when moving through an allies zone of control. All forms of movement, including instant teleportation, provoke. Allies must also be within this aura to gain these benefits. | F15: 20/20 | G15: 4W,5(W|B),(12) 7W,9(W|B),(21) | H15: 6 | J15: 6 | M15: 6 | O15: 20 | P15: 40
A16: =ISBLANK(B16)+ISBLANK(C16)+ISBLANK(D16)+ISBLANK(E16)+ISBLANK(F16)+ISBLANK(G16) -> 0 | B16: Aura | C16: Rally Morale | D16: Your allies may use your willpower in place of their own, or their willpower + RANK (whichever is higher) when resisting most effects. This does not apply to drain checks. | E16: Your allies may use your willpower in place of their own, or their willpower + RANK (whichever is higher) when resisting most effects. This does not apply to drain checks. | F16: 10 | G16: 6W,6(W|U|G),(15) | H16: 6 | I16: 0 | J16: 0 | K16: 0 | L16: 0 | M16: 6 | O16: 10 | P16: 20 | Q16: 30
A17: =ISBLANK(B17)+ISBLANK(C17)+ISBLANK(D17)+ISBLANK(E17)+ISBLANK(F17)+ISBLANK(G17) -> 0 | B17: Aura | C17: Rallying Aura | D17: bonus vs. fear and charm, bonus on combat | E17: Resist fear, resist charm, combat; +1 die per rank | F17: 15 30 45 | G17: 3W,4(W|R),(9) 7W,7(W|R),(18) 10W,11(W|R),(27) | H17: 3 | I17: 0 | J17: 0 | K17: 3 | L17: 0 | M17: 6 | O17: 15 | P17: 45 | Q17: 90
A18: =ISBLANK(B18)+ISBLANK(C18)+ISBLANK(D18)+ISBLANK(E18)+ISBLANK(F18)+ISBLANK(G18) -> 0 | B18: Aura | C18: Rallying Spirit | D18: Your combat prowess brings inspiration to your allies, their morale confers healing | E18: When you make a successful melee attack you may heal an ally within CHA*5 ft RANK*4 meat or RANK*8 stam health. (This healing is subject to normal healing rules.) | F18: 10 | G18: 6W,(12) 9W,(18) 12W,(24) 18W,(30) | H18: 8 | M18: 8 | O18: 10 | P18: 20 | Q18: 30 | R18: 40
A19: =ISBLANK(B19)+ISBLANK(C19)+ISBLANK(D19)+ISBLANK(E19)+ISBLANK(F19)+ISBLANK(G19) -> 0 | B19: Aura | C19: Repositioning Aura | D19: When you hit with an attack you may designate an ally within your aura to take a move action. | E19: When you hit with an attack you may designate an ally within your aura to move up to their movement rate. | F19: 20 | G19: 3W,(15) | O19: 20
A20: =ISBLANK(B20)+ISBLANK(C20)+ISBLANK(D20)+ISBLANK(E20)+ISBLANK(F20)+ISBLANK(G20) -> 0 | B20: Aura | C20: Shielding Aura | D20: When you make a parry, all allies within the aura gain 1 temp hp | E20: When you succesfully block or parry, all allies except you within the aura gain 2 temp hp | F20: 40 | G20: 7W,(21) | O20: 40
A21: =ISBLANK(B21)+ISBLANK(C21)+ISBLANK(D21)+ISBLANK(E21)+ISBLANK(F21)+ISBLANK(G21) -> 0 | B21: Aura | C21: Skill Teamwork | D21: Boost allies' skills for skills you have high ranks in (DEPRECATED) | E21: DEPRECATED Rank 1: up to 2 Rank 2: up to 4 Rank 3: up to 6 Rank 4: up to 8 | F21: 20,40,60,80 | G21: 1W,1G,1(W|G),(6) per | H21: 4 | I21: 4 | J21: 0 | K21: 0 | L21: 4 | M21: 4 | O21: 20 | P21: 60 | Q21: 120 | R21: 200
A22: =ISBLANK(B22)+ISBLANK(C22)+ISBLANK(D22)+ISBLANK(E22)+ISBLANK(F22)+ISBLANK(G22) -> 0 | B22: Aura | C22: Slow Aura | D22: increase initiative cost of enemy actions | E22: Enemy's actions cost 1+(RANK) more initiative so long as they are within (5*CHA feet) of you. If another effect would inflict a penalty on the initiative cost of actions only the highest penalty applies. | F22: 10 15 20 | G22: 3U,4(W|U),(9) 7U,7(W|U),(18) 10U,11(W|U),(27) | H22: 6 | I22: 6 | J22: 6 | K22: 0 | L22: 0 | M22: 6 | O22: 10 | P22: 25 | Q22: 45
A23: =ISBLANK(B23)+ISBLANK(C23)+ISBLANK(D23)+ISBLANK(E23)+ISBLANK(F23)+ISBLANK(G23) -> 0 | B23: Aura | C23: Warleader | D23: Allies can attack right after you with a bonus. | E23: The first time you attack each turn all allies within range may take their turn immediately after yours. An ally who chooses to do so may only move or make attacks during that turn. Allies who make use of this ability gain a stacking, refreshing +1 dice to all attack, block, parry rolls until the end of their next turn. The maximum benefit of this bonus is your CHA. | F23: 50 | G23: 9W,9R,(24) | O23: 50
A24: =ISBLANK(B24)+ISBLANK(C24)+ISBLANK(D24)+ISBLANK(E24)+ISBLANK(F24)+ISBLANK(G24) -> 0 | B24: Buff | C24: All outta Bubblegum | D24: various grapple, melee roughness bonuses | E24: Body Buff RANK-1 damage dampening ignore RANK points of wound penalty +RANK vs. knockdown, disarm, trip, resisting grapple Melee attacks trigger knockdown on hit. Target rolls physical resist or gymnastics vs. unsoaked damage. Enemies that fail to escape your grapples take damage as if you made the grapple attack action against them Ignore half an enemy's armor with your grapple attacks | F24: 20/30/40 | G24: 4(R|G),(9) 9(R|G),(18) 13(R|G),(27) | K24: 3 | L24: 3 | M24: 6 | O24: 20 | P24: 50 | Q24: 90
A25: =ISBLANK(B25)+ISBLANK(C25)+ISBLANK(D25)+ISBLANK(E25)+ISBLANK(F25)+ISBLANK(G25) -> 0 | B25: Buff | C25: Arcane Conduit | D25: Casting spells | E25: Body Buff Casting a spell generates a mana charge. Charges may be expended as follows 2-Spent to mitigate an overload (per 1) 2-Spent in place of init costs on counterspelling/redirecting (per 5) 2-Spent to mitigate a counterspell/redirect attempt against one of your spells (-3 dice to opposed attempt per) Max charges = 2*RANK These charges decay after one minute of not generating nor using charges. If you would overflow your limit on charges take drain equal to the overflow amount. You shed sparking magical light (as a torch) while you have at least 2 charges. At Rank 2: Centering generates 1 charge, every point of drain you take from spellcasting generates 1 charge. At Rank 3: All charge generation is increased by +1 | F25: 30/40/80 | G25: 4U,4R,(18) 6U,6R,(24) 8U,8R,(30) | I25: 7 | K25: 7 | M25: 14 | O25: 30 | P25: 70 | Q25: 150
A26: =ISBLANK(B26)+ISBLANK(C26)+ISBLANK(D26)+ISBLANK(E26)+ISBLANK(F26)+ISBLANK(G26) -> 0 | B26: Buff | C26: Avatar of Malice | D26: Empower attacks, lifesteal, ignore full defense | E26: Body buff. All damage you deal is applied as Dark damage post mitigation. Enemies need to spend (5) in order for their total defense to apply against your attack. Whenever your melee attack deals damage to one or more targets gain 2 temp hp, your temp hp may stack. You treat all incoming dark damage and dark damage you suffer as normal damage. After damage is calculated against you, you may move up to (WIL/2) points of it to the delayed track. At the end of the round you lose health equal to the damage in the delayed track, the track then empties. | F26: 100 | G26: 24B,(30) | J26: 20 | M26: 20 | O26: 100
A27: =ISBLANK(B27)+ISBLANK(C27)+ISBLANK(D27)+ISBLANK(E27)+ISBLANK(F27)+ISBLANK(G27) -> 0 | B27: Buff | C27: Avatar of the Heart | D27: Let there be heals | E27: Body Buff When your healing effects heal a creature for at least 1 health you also grant them 2 temp hp. This temp HP can stack on existing temp hp. You may spend 1L in place of any drain you suffer as part of casting a healing effect, this also mitigates all drain for recipients of this healing effect. you may take 3 on all healing rolls You may trigger healing effects as an interrupt at (5) | F27: 100 | G27: 24W,(30) | H27: 20 | M27: 20 | O27: 100
A28: =ISBLANK(B28)+ISBLANK(C28)+ISBLANK(D28)+ISBLANK(E28)+ISBLANK(F28)+ISBLANK(G28) -> 0 | B28: Buff | C28: Bastion | D28: Defensive bonuses, reduced offensive power | E28: half Action. Increase damage dampening by RANK+2. Reduce the starting power of your attacks by RANK+2. This is a body buff | F28: 50 per | G28: 3W,(15) 5W,(21) 6W,(27) | H28: 6 | I28: 0 | J28: 0 | K28: 0 | L28: 0 | M28: 6 | O28: 50 | P28: 100 | Q28: 150
A29: =ISBLANK(B29)+ISBLANK(C29)+ISBLANK(D29)+ISBLANK(E29)+ISBLANK(F29)+ISBLANK(G29) -> 0 | B29: Buff | C29: Bonemonger | D29: Successful attacks generate a temp hp shield, can detonate temp hp shield | E29: Successful attacks generate 2 temp hp. You may detonate your temp hp, discharging the buff, as a full action to deal BOD+temp hp DV as a 10ft AoE attack (attacking with your weapon skill or spellcasting dicepool). This is a body buff. | F29: 40 | G29: 7W,7B,(18) | O29: 40
A30: =ISBLANK(B30)+ISBLANK(C30)+ISBLANK(D30)+ISBLANK(E30)+ISBLANK(F30)+ISBLANK(G30) -> 0 | B30: Buff | C30: Brambleward | D30: Ward against targeted magical effects, discharge for a burst of strength | E30: half action. Gain +3*RANK against targeted magical effects until the end of this round. You may discharge this effect to get +2 STR *RANK on one attempted action. | F30: 10,20,30 | G30: 4G,(9) 9G,(18) 13G,(27) | L30: 6 | M30: 6 | O30: 10 | P30: 30 | Q30: 60
A31: =ISBLANK(B31)+ISBLANK(C31)+ISBLANK(D31)+ISBLANK(E31)+ISBLANK(F31)+ISBLANK(G31) -> 0 | B31: Buff | C31: Charge Weapon | D31: Hold a spell in a weapon to be discharged upon striking | E31: You can cast spells into your weapon(s). The spells are discharged upon striking an opponent, one at a time, in the order they were cast in. -Spells that normally target dodge automatically hit with 0 net hits. In the case of AoE effects produced off this (RULING NEEDED) -Spells that target mental or physical resolve as normal. Casting a spell into a weapon is a half action. For every half action spent since the start of your last turn casting spells into your weapon(s) you may cast an additional spell as part of the half action. You may store up to (cast stat) spells at one time and you can only store spells of up to 1+(cast stat / 2) force. If the weapon leaves your possession for a minute all charges dissipate. Stored charges dissipate an hour after the last charge was added. | F31: 20 | G31: 3U,3R,(12) | I31: 6 | K31: 6 | M31: 6 | O31: 20
A32: =ISBLANK(B32)+ISBLANK(C32)+ISBLANK(D32)+ISBLANK(E32)+ISBLANK(F32)+ISBLANK(G32) -> 0 | B32: Buff | C32: Conjure weapon / armor | D32: Summon personalized weapon / armor, functions while in your keeping but phases out for others | E32: Binding weapons and/or armor is accomplished during one hour of downtime. You may summon any or all of the bound weapons/armor as if drawing (half), or dismiss them as if sheathing (half). When an item is dismissed it exists in a pocket dimension and access can be prevented by effects that limit extradimensional travel. Dismissed items count as attended. You may summon bound equipment back to you granted it has been at most one minute since you last made contact with it. If it is attended the attender must be willing. You are aware of the general direction your bound equipment is in if you become separated from it. You may bind one set of armor and (two one handed weapons or one two handed weapon) per rank. | F32: 5 per | G32: 1W,(6) | H32: 4 | M32: 4 | O32: 5 | P32: 10 | Q32: 15 | R32: 20 | S32: 25 | T32: 30 | U32: 35 | V32: 40 | W32: 45 | X32: 50
A33: =ISBLANK(B33)+ISBLANK(C33)+ISBLANK(D33)+ISBLANK(E33)+ISBLANK(F33)+ISBLANK(G33) -> 0 | B33: Buff | C33: Crisp and Cauterize | D33: Dealing direct fire damage procs a heal Healing procs a firebolt | E33: Body Buff. Whenever your attack or ability deals fire damage to a target you may heal an ally within 60ft for up to an equivalent amount of health. Whenever you heal an ally you may generate a single target ranged firebolt as per Elemental Blast, at DV-1 of default This ability cannot trigger itself | F33: 40 | G33: 9W,9R,(24) | O33: 40
A34: =ISBLANK(B34)+ISBLANK(C34)+ISBLANK(D34)+ISBLANK(E34)+ISBLANK(F34)+ISBLANK(G34) -> 0 | B34: Buff | C34: Deflecting Miasma | D34: More armor vs. ranged attacks, less armor vs. melee attack | E34: Gain RANK armor against ranged attacks, take a penalty of RANK armor against melee attacks. Activating this buff is a simple action. | F34: 10 | G34: ,(15) | O34: 10
A35: =ISBLANK(B35)+ISBLANK(C35)+ISBLANK(D35)+ISBLANK(E35)+ISBLANK(F35)+ISBLANK(G35) -> 0 | B35: Buff | C35: Displacer | D35: You occupy two adjacent squares, appearing to flicker between them. | E35: Body Buff Gain +3 on all defensive checks (not mental or physical resist) You occupy two adjacent squares. You may act from either position that you occupy. You may pass through thin obstacles at the cost of 5ft of movement. You can pay (5) init to solidify in one spot at any time, or a half action during your turn, stabilizing the effect until you spend a Extra action to resume it. | F35: 20 | G35: 3U,4(U|G),(15) | I35: 4 | L35: 4 | M35: 8 | O35: 20
A36: =ISBLANK(B36)+ISBLANK(C36)+ISBLANK(D36)+ISBLANK(E36)+ISBLANK(F36)+ISBLANK(G36) -> 0 | B36: Buff | C36: Duty's Ward | D36: Move to punish those who threaten your selected ally | E36: This buff links you and one ally (within 60ft on activation) and lasts 24 hours or until one recipient opts to dismiss it as a full action. You are aware of when the linked ally is threatened or hurt. You can sense the rough direction the linked ally is in. Enemies taking actions that target the ally but not you provoke attacks of opportunity. Such a triggering action also grants 10ft of movement if that would allow you to move to threaten the triggering enemy. | F36: 30 | G36: 9W,(12) | O36: 30
A37: =ISBLANK(B37)+ISBLANK(C37)+ISBLANK(D37)+ISBLANK(E37)+ISBLANK(F37)+ISBLANK(G37) -> 0 | B37: Buff | C37: Earthward | D37: Generates temp HP and 3 lightning resist | E37: Body Buff. Every minute and when you activate this ability you generate 2 temporary hp up to half your maximum temp hp. You also gain 6 lightning res. _________________ Temporary HP accrues at the start of each round instead of every minute. | F37: 20,30 | G37: 6G,(12) 12G,(24) | O37: 20 | P37: 50
A38: =ISBLANK(B38)+ISBLANK(C38)+ISBLANK(D38)+ISBLANK(E38)+ISBLANK(F38)+ISBLANK(G38) -> 0 | B38: Buff | C38: Elemental Body (Acid) | D38: Acid: acid retal burst | E38: Gain for the duration Resist Acid: 6*RANK Whenever you are struck by a corporeal attack that does at least 1 point of damage all adjacent creatures must soak (armor soak) acid damage equal to (BOD + 3*RANK). You may channel the acid into an area attack centered on you (you are unaffected by this attack) with (BOD/2*5 ft radius). DV = (BOD+3* RANK)(resolve as a spellcast or attack as desired). Doing so ends the benefits of Elemental Body. This is a body buff. Activating this buff is a half action, channeling the acid is a full action. | F38: 15/25/35 | G38: 2(B|G),(9) 4(B|G),(18) 6(B|G),(27) | H38: 0 | I38: 0 | J38: 6 | K38: 0 | L38: 0 | M38: 6 | O38: 15 | P38: 40 | Q38: 75
A39: =ISBLANK(B39)+ISBLANK(C39)+ISBLANK(D39)+ISBLANK(E39)+ISBLANK(F39)+ISBLANK(G39) -> 0 | B39: Buff | C39: Elemental Body (Air) | D39: Flight, increased movement speed, deflection, immunity to gases/inhaled poisons, wind blast discharge | E39: You gain the ability to (glide, fly as per flight N, fly as per flight NN), your movement speed increases by 10*RANK, you gain +RANK dice vs. ranged attacks, immunity to gases and inhaled poisons, treat wind based vision penalties as RANK steps lower. As a full action you may discharge this buff to produce a (BOD/2)*5ft cone of rushing air, rolling weapon skill or spellcasting vs. all targets in the cone (eDV = BOD + 3*rank). Targets Resist with Physical Resist and soak with Physical soak. Targets are pushed (unsoaked eDV)/2 *5ft directly away from you. | F39: 15/25/35 | G39: 2(W|U),(9) 4(W|U),(18) 6(W|U),(27) | O39: 15 | P39: 40 | Q39: 75
A40: =ISBLANK(B40)+ISBLANK(C40)+ISBLANK(D40)+ISBLANK(E40)+ISBLANK(F40)+ISBLANK(G40) -> 0 | B40: Buff | C40: Elemental Body (Cold) | D40: Cold: chilling presence | E40: Gain for the duration Resist Cold: 6*RANK Creatures that start their turn adjacent lose RANK initiative as if suffering damage from a cold effect. Resistance to cold mitigates this at a 1:1 ratio. You may channel the chill into an area attack centered on you (you are unaffected by this attack) with (BOD/2*5 ft radius). DV = (BOD+ 3*RANK)(resolve as a spellcast or attack as desired). Doing so ends the benefits of Elemental Body. This is a body buff. Activating this buff is a half action, channeling the cold is a full action. | F40: 15/25/35 | G40: 2U,(9) per | H40: 0 | I40: 6 | J40: 0 | K40: 0 | L40: 0 | M40: 6 | O40: 15 | P40: 40 | Q40: 75
A41: =ISBLANK(B41)+ISBLANK(C41)+ISBLANK(D41)+ISBLANK(E41)+ISBLANK(F41)+ISBLANK(G41) -> 0 | B41: Buff | C41: Elemental Body (Dark) | D41: Ebody dark, resist dark, (active) | E41: Gain for the duration Resist Dark: 6*RANK Whenever you are struck by a corporeal attack that does at least 1 point of damage you produce an obscuring miasma in your square that lasts until the end of the round/next round/next next round. You may channel the darkness into an obscuring miasma centered on you, radius = (BOD/2 -1+RANK), that lasts until the end of the next round. The miasma blocks all light for everyone except you. Doing so ends the benefits of Elemental Body. This is a body buff. Activating this buff is a half action, channeling the darkness is a full action. | F41: 15/25/35 | G41: 2(B),(9) 4(B),(18) 6(B),(27) | O41: 15 | P41: 40 | Q41: 75
A42: =ISBLANK(B42)+ISBLANK(C42)+ISBLANK(D42)+ISBLANK(E42)+ISBLANK(F42)+ISBLANK(G42) -> 0 | B42: Buff | C42: Elemental Body (Earth) | D42: Earth: | E42: Gain for the duration Damage Dampening: 2 You may channel the strength of earth to mitigate one physical attack. Gaining an additional 3*RANK Damage Dampening. Doing so ends the benefits of Elemental Body after resolving the damage for that attack. This is a body buff. Activating this buff is a half action, channeling the earth is a nonaction. | F42: 15/25/35 | G42: 2G,(9) per | H42: 0 | I42: 0 | J42: 0 | K42: 0 | L42: 6 | M42: 6 | O42: 15 | P42: 40 | Q42: 75
A43: =ISBLANK(B43)+ISBLANK(C43)+ISBLANK(D43)+ISBLANK(E43)+ISBLANK(F43)+ISBLANK(G43) -> 0 | B43: Buff | C43: Elemental Body (Fire) | D43: Fire: Burning presence, fire burst | E43: Gain for the duration Resist Fire: 6*RANK Creatures that start their turn adjacent must save or catch fire as if affected by a (BOD+2*RANK) fire attack. At the end of each round adjacent objects save or catch fire. You may channel the fire into an area attack centered on you (you are unaffected by this attack) with (BOD/2*5 ft radius). DV = (BOD+ 3*RANK)(resolve as a spellcast or attack as desired). Doing so ends the benefits of Elemental Body. This is a body buff. Activating this buff is a half action, channeling the fire is a full action. | F43: 15/25/35 | G43: 2R,(9) per | H43: 0 | I43: 0 | J43: 0 | K43: 6 | L43: 0 | M43: 6 | O43: 15 | P43: 40 | Q43: 75
A44: =ISBLANK(B44)+ISBLANK(C44)+ISBLANK(D44)+ISBLANK(E44)+ISBLANK(F44)+ISBLANK(G44) -> 0 | B44: Buff | C44: Elemental Body (Lightning) | D44: Lightning: lightning presence, lightning leap | E44: Gain for the duration Resist Lightning: 6*RANK Creatures that are adjacent to you that take lightning damage take an additional point of lightning damage as if struck by a separate lightning effect. This ability cannot trigger itself. You may channel the lightning into a line attack originating from you with up to (BOD*10 ft length). DV = (BOD+ 3*RANK)(resolve as a spellcast or attack as desired). You may teleport to the farthest square of the target area. Using the attack function ends the benefits of Elemental Body. This is a body buff. Activating this buff is a half action, channeling the lightning is a full action. | F44: 15/25/35 | G44: 2R,(9) per | H44: 0 | I44: 3 | J44: 0 | K44: 3 | L44: 0 | M44: 6 | O44: 15 | P44: 40 | Q44: 75
A45: =ISBLANK(B45)+ISBLANK(C45)+ISBLANK(D45)+ISBLANK(E45)+ISBLANK(F45)+ISBLANK(G45) -> 0 | B45: Buff | C45: Elemental Body (Radiant) | D45: Ebody radiant, resist radiant, (active) | E45: Gain for the duration Resist Radiant: 6*RANK Whenever you are struck by a corporeal attack that does at least 1 point of damage all adjacent creatures must avoid automatic blinding (until end of round), dodge or physical res vs. (BOD/2+rank-2) automatic hits. You may channel the radiance into an area attack centered on you (you are unaffected by this attack) with ((BOD/2+1)*5 ft radius), resolve as an attack or spellcast as desired. This attack does no damage, may be dodged or physically resisted, and only requires 3 net hits to blind (blinding until end of next round). This a. Doing so ends the benefits of Elemental Body. This is a body buff. Activating this buff is a half action, channeling the radiance is a full action. | F45: 15/25/35 | G45: 2(W),(9) 4(W),(18) 6(W),(27)
A46: =ISBLANK(B46)+ISBLANK(C46)+ISBLANK(D46)+ISBLANK(E46)+ISBLANK(F46)+ISBLANK(G46) -> 0 | B46: Buff | C46: Envenom Weapons | D46: Poison weapons as weapon buff | E46: Damage adjusted by -4 Victim injured by weapon soaks venom at end of round with phys soak, DV = your BOD As usual for poison effects subsequent applications of the poison during the same round raise the end of round DV by 2. | F46: 20 | G46: 7(B|G),(9) | O46: 20
A47: =ISBLANK(B47)+ISBLANK(C47)+ISBLANK(D47)+ISBLANK(E47)+ISBLANK(F47)+ISBLANK(G47) -> 0 | B47: Buff | C47: Escalation | D47: Lose mana each turn, but guarantee a growing drain soak value | E47: Costs 1 mana to activate. Pay 1 mana at the start of your turn or this buff expires. Let X be the number of turns this buff has been active, counting the activation turn as the first turn. You may replace the result of your drain soak roll with X after rolling. Activating this buff is a simple action. | F47: 20 | G47: 10R,(21) | O47: 20
A48: =ISBLANK(B48)+ISBLANK(C48)+ISBLANK(D48)+ISBLANK(E48)+ISBLANK(F48)+ISBLANK(G48) -> 0 | B48: Buff | C48: Fleetfoot Blessing | D48: 1 temp hp, movespeed bonus while this temp hp lasts | E48: grant 2 temp HP, increase your movement speed by 10 for 10 rounds. half action. | F48: 5 | G48: 3W,3R,(12) | H48: 4 | K48: 4 | M48: 8 | O48: 5
A49: =ISBLANK(B49)+ISBLANK(C49)+ISBLANK(D49)+ISBLANK(E49)+ISBLANK(F49)+ISBLANK(G49) -> 0 | B49: Buff | C49: Imbue Weapon (Acid) | D49: Half action to apply element to attended weapons, dismiss as Extra action. Changes weapon damage type to element. Damage adjusted by -1 | E49: half action to apply element to attended weapons, dismiss as Extra action. Changes weapon damage type to element. Damage adjusted by -2 | F49: 10 | G49: 4(B|G),(9) | H49: 0 | I49: 0 | J49: 6 | K49: 0 | L49: 6 | M49: 6 | O49: 10
A50: =ISBLANK(B50)+ISBLANK(C50)+ISBLANK(D50)+ISBLANK(E50)+ISBLANK(F50)+ISBLANK(G50) -> 0 | B50: Buff | C50: Imbue Weapon (Cold) | D50: Half action to apply element to attended weapons, dismiss as Extra action. Changes weapon damage type to element. Damage adjusted by -1 | E50: half action to apply element to attended weapons, dismiss as Extra action. Changes weapon damage type to element. Damage adjusted by -2 | F50: 10 | G50: 4U,(9) | H50: 0 | I50: 6 | J50: 0 | K50: 0 | L50: 0 | M50: 6 | O50: 10
A51: =ISBLANK(B51)+ISBLANK(C51)+ISBLANK(D51)+ISBLANK(E51)+ISBLANK(F51)+ISBLANK(G51) -> 0 | B51: Buff | C51: Imbue Weapon (Dark) | D51: Half action to apply element to attended weapons, dismiss as Extra action. Changes weapon damage type to element. Damage adjusted by -1 | E51: half action to apply element to attended weapons, dismiss as Extra action. Changes weapon damage type to element. Damage adjusted by -2 | F51: 10 | G51: 4B,(9) | H51: 0 | I51: 0 | J51: 0 | K51: 6 | L51: 0 | M51: 6 | O51: 10
A52: =ISBLANK(B52)+ISBLANK(C52)+ISBLANK(D52)+ISBLANK(E52)+ISBLANK(F52)+ISBLANK(G52) -> 0 | B52: Buff | C52: Imbue Weapon (Fire) | D52: Half action to apply element to attended weapons, dismiss as Extra action. Changes weapon damage type to element. Damage adjusted by -1 | E52: half action to apply element to attended weapons, dismiss as Extra action. Changes weapon damage type to element. Damage adjusted by -2 | F52: 10 | G52: 4R,(9) | H52: 0 | I52: 0 | J52: 0 | K52: 6 | L52: 0 | M52: 6 | O52: 10
A53: =ISBLANK(B53)+ISBLANK(C53)+ISBLANK(D53)+ISBLANK(E53)+ISBLANK(F53)+ISBLANK(G53) -> 0 | B53: Buff | C53: Imbue Weapon (Lightning) | D53: Half action to apply element to attended weapons, dismiss as Extra action. Changes weapon damage type to element. Damage adjusted by -1 | E53: half action to apply element to attended weapons, dismiss as Extra action. Changes weapon damage type to element. Damage adjusted by -2 | F53: 10 | G53: 4R,(9) | H53: 0 | I53: 3 | J53: 0 | K53: 3 | L53: 0 | M53: 6 | O53: 10
A54: =ISBLANK(B54)+ISBLANK(C54)+ISBLANK(D54)+ISBLANK(E54)+ISBLANK(F54)+ISBLANK(G54) -> 0 | B54: Buff | C54: Imbue Weapon (Radiant) | D54: Half action to apply element to attended weapons, dismiss as Extra action. Changes weapon damage type to element. Damage adjusted by -1 | E54: half action to apply element to attended weapons, dismiss as Extra action. Changes weapon damage type to element. Damage adjusted by -2 | F54: 10 | G54: 4W,(9) | H54: 0 | I54: 0 | J54: 0 | K54: 6 | L54: 0 | M54: 6 | O54: 10
A55: =ISBLANK(B55)+ISBLANK(C55)+ISBLANK(D55)+ISBLANK(E55)+ISBLANK(F55)+ISBLANK(G55) -> 0 | B55: Buff | C55: Martial Spirit | D55: No aura, two stances, combine maneuvers | E55: Body Buff You may not have an aura active You may have two stances active You may combine two maneuvers as part of one action where both could apply. If they both have initiative costs, you only need to pay the higher one. | F55: 100 | G55: 8W,8R,8(W|R),(30) | H55: 7 | K55: 7 | M55: 14 | O55: 100 | Y55: TR10
A56: =ISBLANK(B56)+ISBLANK(C56)+ISBLANK(D56)+ISBLANK(E56)+ISBLANK(F56)+ISBLANK(G56) -> 0 | B56: Buff | C56: Press your luck | D56: Spend (2?3?) points of luck, for the rest of the round all your dice explode | E56: Nonaction. Spend 2 luck, For the rest of the round all your dice explode. | F56: 10 | G56: 9R,(18) | H56: 0 | I56: 0 | J56: 0 | K56: 12 | L56: 0 | M56: 12 | O56: 10
A57: =ISBLANK(B57)+ISBLANK(C57)+ISBLANK(D57)+ISBLANK(E57)+ISBLANK(F57)+ISBLANK(G57) -> 0 | B57: Buff | C57: Purging Bubble | D57: 1 temp hp, 1 purge roll on apply | E57: half action. Reduce the (e)DV of one ongoing status on the target by 5. Target gains 1 temp hp | F57: 5 | G57: 7W,(9) | H57: 6 | L57: 6 | M57: 6 | O57: 5 | Y57: probably too cheap at 5
A58: =ISBLANK(B58)+ISBLANK(C58)+ISBLANK(D58)+ISBLANK(E58)+ISBLANK(F58)+ISBLANK(G58) -> 0 | B58: Buff | C58: Shadow Partner | D58: Create a fragile clone of yourself with half stats that mirrors your actions | E58: Extra action, spend 1 L. Create a shadowy clone of yourself in an adjacent square. It acts on your initiative count, has half your dicepool for any roll before modifiers. The clone cannot spend initiative on any actions, nor can it spend luck. The clone has its own health and cannot be healed, taking all damage as lethal. The clone does not suffer wound penalties. You can perceive everything your clone perceives. Outside of these limitations, your clone functions with your abilities. | F58: 100 | G58: 8U,8B,8(U|B),(30) | I58: 10 | J58: 10 | M58: 20 | O58: 100
A59: =ISBLANK(B59)+ISBLANK(C59)+ISBLANK(D59)+ISBLANK(E59)+ISBLANK(F59)+ISBLANK(G59) -> 0 | B59: Buff | C59: Shared fate | D59: split damage with ally | E59: full Action. Touch range, targets ally and self. For the duration all damage suffered by either recipient of this buff is split equally (primary target takes higher value in case of odd valued damage). Split damage after all resistances and rolls are concluded. | F59: 10 | G59: 4W,(6) | H59: 2 | I59: 0 | J59: 0 | K59: 0 | L59: 2 | M59: 4 | O59: 10
A60: =ISBLANK(B60)+ISBLANK(C60)+ISBLANK(D60)+ISBLANK(E60)+ISBLANK(F60)+ISBLANK(G60) -> 0 | B60: Buff | C60: Soulward | D60: Spend X health, get 2X temp hp | E60: half Action. Spend X health to gain 2X temp hp. | F60: 10 | G60: 6B,(12) | H60: 0 | I60: 0 | J60: 10 | K60: 0 | L60: 0 | M60: 10 | O60: 10
A61: =ISBLANK(B61)+ISBLANK(C61)+ISBLANK(D61)+ISBLANK(E61)+ISBLANK(F61)+ISBLANK(G61) -> 0 | B61: Buff | C61: Spellforged Strikes | D61: Gain martial prowess for a short time after casting spells | E61: Gain +1 dice to weapon attack rolls until the end of the next round, cumulative and refreshing, when you cast a spell. While you are benefiting from these extra dice you may make an additional attack with a wielded weapon as part of a melee attack, splitting your dicepool as normal. | F61: 40 | G61: 18(W|U|R),(24) | O61: 40
A62: =ISBLANK(B62)+ISBLANK(C62)+ISBLANK(D62)+ISBLANK(E62)+ISBLANK(F62)+ISBLANK(G62) -> 0 | B62: Buff | C62: Swarmform | D62: Shapeshift into a cohesive swarm of small creatures | E62: Gain +3 bonus (defense roll only) vs. single target attacks and effects Take -5 penalty (defense and soak) vs. area attacks and effects Damage taken from single target attacks cannot exceed 10 You may disperse/condense into a swarm as a half action. | F62: 30 | G62: 14G,(18) | L62: 12 | M62: 12 | O62: 30
A63: =ISBLANK(B63)+ISBLANK(C63)+ISBLANK(D63)+ISBLANK(E63)+ISBLANK(F63)+ISBLANK(G63) -> 0 | B63: Buff | C63: The Quick and The Dead | D63: boost dodge, take more damage when hit | E63: half Action. Gain RANK free hits on all dodge rolls. Your damage dampening is reduced by (2+4*RANK). | F63: 30/40/50 | G63: 14(U|B|R),(18) | J63: 6 | K63: 6 | M63: 6 | O63: 30 | P63: 70 | Q63: 120
A64: =ISBLANK(B64)+ISBLANK(C64)+ISBLANK(D64)+ISBLANK(E64)+ISBLANK(F64)+ISBLANK(G64) -> 0 | B64: Buff | C64: Titan Armor | D64: Gain mitigation dice, slow down | E64: half Action. Gain 2 Armor soak per RANK for RANK*10 rounds. Your speed is halved. This is a body buff. | F64: 5 per | G64: 4G,(6) 9G,(12) 14G,(18) 19G,(24) 24G,(30) | L64: 4 | M64: 4 | O64: 5 | P64: 10 | Q64: 15 | R64: 20 | S64: 25
A65: =ISBLANK(B65)+ISBLANK(C65)+ISBLANK(D65)+ISBLANK(E65)+ISBLANK(F65)+ISBLANK(G65) -> 0 | B65: Buff | C65: Vengeful Protector | D65: Buff up to one ally, attacks on them provoke from you | E65: Simple action, buff an ally within 30 ft. Attacks that target that ally provoke an opportunity attack from you (Only creatures that you threaten provoke opportunity attacks from you). | F65: 5 | G65: 12W,(18) | O65: 5
A66: =ISBLANK(B66)+ISBLANK(C66)+ISBLANK(D66)+ISBLANK(E66)+ISBLANK(F66)+ISBLANK(G66) -> 0 | B66: Flaw | C66: Blindness | D66: You are blind | E66: You are blind. Whenever the GM deems that this flaw impacts a scene they may award you 1 LUCK. | F66: 0 | G66: WURBG,(0) | H66: 1 | I66: 1 | J66: 1 | K66: 1 | L66: 1 | M66: 1 | O66: 0
A67: =ISBLANK(B67)+ISBLANK(C67)+ISBLANK(D67)+ISBLANK(E67)+ISBLANK(F67)+ISBLANK(G67) -> 0 | B67: Maneuver | C67: All in | D67: Burn initiative for a powerful strike | E67: Spend the rest of your initiative as part of an attack. Gain +1 free hit for every (10) spent in this way, rounding up. _________________ Instead for every (9) spent _________________ Instead for every (8) | F67: 5/10/15 | G67: 7R,(9) 14R,(18) 20R,(27) | H67: 0 | I67: 0 | J67: 0 | K67: 10 | L67: 0 | M67: 10 | O67: 5 | P67: 15 | Q67: 30
A68: =ISBLANK(B68)+ISBLANK(C68)+ISBLANK(D68)+ISBLANK(E68)+ISBLANK(F68)+ISBLANK(G68) -> 0 | B68: Ritual | C68: Arcane Mark | D68: Put a magic mark on something | E68: Place an invisible magical mark on an object after 1 minute of casting. The mark is not invisible to you, and up to (cast stat) others of your choice present upon casting. The mark may be viewed normally with Perceive Magic). | F68: 5 | G68: 1(W|U),(6) | H68: 4 | I68: 4 | M68: 4 | O68: 5
A69: =ISBLANK(B69)+ISBLANK(C69)+ISBLANK(D69)+ISBLANK(E69)+ISBLANK(F69)+ISBLANK(G69) -> 0 | B69: Maneuver | C69: Arcane Rush | D69: Make a charge, if you connect cast a single target spell | E69: Make a charge attack. If the attack deals damage you may cast a single target spell on the charge victim or a single target spell on yourself. | F69: 40 | G69: 7R,7G,(18) | O69: 40
A70: =ISBLANK(B70)+ISBLANK(C70)+ISBLANK(D70)+ISBLANK(E70)+ISBLANK(F70)+ISBLANK(G70) -> 0 | B70: Maneuver | C70: Assisted Escape | D70: Target an ally, they may move up to their movement speed. After moving, apply temp hp. | E70: Target ally may move up to their walking speed, after moving they gain 1 temp hp. half action. | F70: 5 | G70: 2W,(3) | H70: 2 | M70: 2 | O70: 5
A71: =ISBLANK(B71)+ISBLANK(C71)+ISBLANK(D71)+ISBLANK(E71)+ISBLANK(F71)+ISBLANK(G71) -> 0 | B71: Maneuver | C71: Avalanche of Blades | D71: Flurry of attacks until missing | E71: (10) Make a melee attack, if this attack hits make another attack at a cumulative -4 penalty to all rolls against the same target, repeat. __________________ Instead at a cumulative -3 penalty | F71: 25/40 | G71: 16(W|R),(21) 24(W|R),(30 | H71: 12 | M71: 12 | O71: 25 | P71: 65
A72: =ISBLANK(B72)+ISBLANK(C72)+ISBLANK(D72)+ISBLANK(E72)+ISBLANK(F72)+ISBLANK(G72) -> 0 | B72: Maneuver | C72: Avatar of Might | D72: +n/+x trample | E72: Up to cha friendly targets get +(cast stat/2) on all dicepools involving STR or BOD, +(cast stat /2) DV on weapon attacks that scale with STR, ignore enemies' full defense. For each subject this benefit expires at the end of their turn. Extra action (10) | F72: 100 | G72: 24G,(30) | O72: 100
A73: =ISBLANK(B73)+ISBLANK(C73)+ISBLANK(D73)+ISBLANK(E73)+ISBLANK(F73)+ISBLANK(G73) -> 0 | B73: Maneuver | C73: Balance the Scales | D73: Equalize wounds with ally | E73: (Touch) Equalize wounds with one ally. If there are an odd number of physical and/or nonlethal wounds you choose who receives the odd numbered wound. | F73: 10 | G73: 9(W|G),(18) | H73: 6 | I73: 0 | J73: 0 | K73: 0 | L73: 6 | M73: 12 | O73: 10
A74: =ISBLANK(B74)+ISBLANK(C74)+ISBLANK(D74)+ISBLANK(E74)+ISBLANK(F74)+ISBLANK(G74) -> 0 | B74: Maneuver | C74: Blade Barrier | D74: Produce a wall of blades that provide cover and harm those crossing it | E74: Produce a contiguous wall of whirling blades and weapons that fills (AGI/2) 5ft cubes. Creatures that end the round inside or move into the wall are subject to a normal melee attack using the stats of a weapon you are currently wielding. The wall lasts until the end of your next turn. You may spend your Extra action to extend the duration of the wall until the end of your turn. You may only have one Blade Barrier active at a time. The Blade Barrier provides cover. | F74: 20 | G74: 10W,(21) | O74: 20
A75: =ISBLANK(B75)+ISBLANK(C75)+ISBLANK(D75)+ISBLANK(E75)+ISBLANK(F75)+ISBLANK(G75) -> 0 | B75: Maneuver | C75: Blinding Bulwark | D75: Blocking enemies has a chance to blind them (REWORK PENDING) | E75: Spend (5) on block to roll a CHA DV attack with spellcasting or weapon skill vs. attacker's mental resist. Target soaks with mental soak and is blinded for a number of rounds equal to the damage the attack would do. | F75: 5 | G75: 7W,(9) | H75: 6 | M75: 6 | O75: 5
A76: =ISBLANK(B76)+ISBLANK(C76)+ISBLANK(D76)+ISBLANK(E76)+ISBLANK(F76)+ISBLANK(G76) -> 0 | B76: Maneuver | C76: Blinding Strike | D76: Attack to blind a target | E76: Make an attack with eDV = weapon DV Phys res Armor Soak 0: no effect 1: the next attack made against the target before the end of the next round benefits from advantageous ground 5: all attacks made against the target before the end of the next round benefit from superior ground 9+: the target is blinded until the end of the next round _____________ eDV = weapon DV + 2 _____________ eDV = weapon DV + 4 | F76: 5/15/25 | G76: 4W,(6) 12W,(15) 19W,(24) | H76: 2 | M76: 2 | O76: 5 | P76: 20 | Q76: 45 | Y76: probably too cheap
A77: =ISBLANK(B77)+ISBLANK(C77)+ISBLANK(D77)+ISBLANK(E77)+ISBLANK(F77)+ISBLANK(G77) -> 0 | B77: Maneuver | C77: Blink | D77: Tactical Teleportation | E77: Extra action, teleport up to your 30ft to a square within line of sight. The next use of this ability costs 10/1/0 more stamina. The stamina cost of this ability decreases by 1 at the end of the round. | F77: 30-45-60 | G77: 7U,(15) 10U,(21) 13U,(27) | I77: 4 | M77: 4 | O77: 30 | P77: 75 | Q77: 135
A78: =ISBLANK(B78)+ISBLANK(C78)+ISBLANK(D78)+ISBLANK(E78)+ISBLANK(F78)+ISBLANK(G78) -> 0 | B78: Maneuver | C78: Blood for Blood | D78: Spend health to boost the damage of a successful hit | E78: Nonaction. After hitting with a weapon attack you may spend 1 health to increase the (e)DV of the attack by 2. You may only do this once per attack. | F78: 20 | G78: 9B,(18) | O78: 20
A79: =ISBLANK(B79)+ISBLANK(C79)+ISBLANK(D79)+ISBLANK(E79)+ISBLANK(F79)+ISBLANK(G79) -> 0 | B79: Maneuver | C79: Bloom Field | D79: Spawn and manipulate blooms for battlefield options | E79: half action: Spawn (BOD) buds on the ground within 50ft in unoccupied spaces. Buds die if you go 100ft from them or one minute passes since a function of this ability is activated. Extra action: Command one or all buds (same command) - Spawn bramble patch: Creates 3 5ft boxes centered on the bud. The brambles are 5ft high and cost double movement for enemies. Allies move normally through the brambles. The brambles grant total cover. This causes the bud to expire.The brambles die when buds would die. - Ensnare: Bud rolls attack (spellcasting or weapon skill) against enemy (dodge block parry), enemy soaks with physical soak and upon failure cannot move or make attacks of opportunity for eDV duration, or unitl they take a full action to free themselves. Buds use your weapon skill or spellcasting dicepool and have DV of 4+ STR. You can target the same creature with multiple buds, in which case the swarming rules apply (each bud past the first does not generate another attack, instead increasing the dicepool by +3) - Teleport: Teleport to a spot adjacent to any bud, you may only do this starting from adjacent to a bud. This does not consume the bud. half action or (5): Create a bud on your location and teleport as above. | F79: 25 | G79: 9G,(18) | L79: 12 | M79: 12 | O79: 25
A80: =ISBLANK(B80)+ISBLANK(C80)+ISBLANK(D80)+ISBLANK(E80)+ISBLANK(F80)+ISBLANK(G80) -> 0 | B80: Maneuver | C80: Bola Arrow | D80: Grapple, trip, disarm with arrow | E80: Grapple, trip, disarm with arrow as part of an attack, don't gain net hits on damage. ___________ Gain half net hits on damage ___________ Gain all net hits on damage | F80: 10/20/30 | G80: 4G,(9) 9G,(18) 13G,(27) | L80: 6 | M80: 6 | O80: 10 | P80: 30 | Q80: 60
A81: =ISBLANK(B81)+ISBLANK(C81)+ISBLANK(D81)+ISBLANK(E81)+ISBLANK(F81)+ISBLANK(G81) -> 0 | B81: Stance | C81: Bolstering Momentum | D81: After a successful attack, activate a buff as a Extra action. | E81: If you successfully hit with a weapon attack this turn you may activate a single buff as a nonaction. | F81: 15 | G81: 14(W|U|B),(18) | O81: 15
A82: =ISBLANK(B82)+ISBLANK(C82)+ISBLANK(D82)+ISBLANK(E82)+ISBLANK(F82)+ISBLANK(G82) -> 0 | B82: Maneuver | C82: Breathstealing Blow | D82: forces save vs. silence | E82: Make an attack with eDV = weapon DV -4 Phys res Armor Soak 0: no effect 1: the target is silenced on its next turn 5: the target is silenced until the end of the round 9: the target is silenced until the end of the next round ______ eDV = weapon DV -2 ______ eDV = weapon DV | F82: 10/20/30 | G82: 4W,(9) 9W,(18) 13W,(27) | H82: 4 | M82: 4 | O82: 10 | P82: 30 | Q82: 60
A83: =ISBLANK(B83)+ISBLANK(C83)+ISBLANK(D83)+ISBLANK(E83)+ISBLANK(F83)+ISBLANK(G83) -> 0 | B83: Maneuver | C83: Burnout | D83: Roll an init die twice, lose access to that init die for the following round. 2 round cooldown. | E83: Roll an init die twice, lose acces to that init die for the following round | F83: 20 | G83: 7R,(9) | K83: 6 | M83: 6 | O83: 20
A84: =ISBLANK(B84)+ISBLANK(C84)+ISBLANK(D84)+ISBLANK(E84)+ISBLANK(F84)+ISBLANK(G84) -> 0 | B84: Maneuver | C84: Butterknifing | D84: Improved sunder | E84: (5) as an additional cost on an attack against an inanimate or attended object. Treat the object's barrier rating as 5 lower. ____________________ (1) As an additional cost ____________________ (0) As an additional cost. This ability funcitonally becomes an optional passive. | F84: 10/20/30 | G84: 4(R|G),(9) 9(R|G),(18) 13(R|G),(27) | K84: 3 | L84: 3 | M84: 6 | O84: 10 | P84: 30 | Q84: 60
A85: =ISBLANK(B85)+ISBLANK(C85)+ISBLANK(D85)+ISBLANK(E85)+ISBLANK(F85)+ISBLANK(G85) -> 0 | B85: Maneuver | C85: Clarion Call | D85: Grant allies option to take extra action when downing an enemy | E85: Nonaction after your attack renders an opponent unconscious All allies within CHA*5 ft may spend (5) and make a single attack or move up to their speed, this movement does not count towards the round's max movement. | F85: 20 | G85: 16W,(21) | H85: 12 | M85: 12 | O85: 20
A86: =ISBLANK(B86)+ISBLANK(C86)+ISBLANK(D86)+ISBLANK(E86)+ISBLANK(F86)+ISBLANK(G86) -> 0 | B86: Maneuver | C86: Commander's Strike | D86: Command an ally to attack | E86: full Action: One ally within CHA*10 ft may make an attack. | F86: 60 | G86: 5W,5R,(21) | O86: 60
A87: =ISBLANK(B87)+ISBLANK(C87)+ISBLANK(D87)+ISBLANK(E87)+ISBLANK(F87)+ISBLANK(G87) -> 0 | B87: Maneuver | C87: Contingency | D87: Invest luck into holding spell until chosen trigger | E87: Spend 1 Luck, you can’t regain this point of luck while you have an active contingency. Cast a spell to be your contingency, noting your current dicepool and other parameters, resisting drain when creating this contingency. Set a condition under which the contingency will trigger... | F87: 30 | G87: 10U,(21) | I87: 14 | M87: 14 | O87: 30
A88: =ISBLANK(B88)+ISBLANK(C88)+ISBLANK(D88)+ISBLANK(E88)+ISBLANK(F88)+ISBLANK(G88) -> 0 | B88: Maneuver | C88: Counter Charge | D88: When an enemy is charging, you may charge to intercept. | E88: (10) when an enemy makes a charge attack, charge the enemy during their movement, attack them, on hit also make an opposed STR check, on success the enemy stops moving and does not get to attack. | F88: 5 | G88: 4W,(6) | H88: 4 | M88: 4 | O88: 5
A89: =ISBLANK(B89)+ISBLANK(C89)+ISBLANK(D89)+ISBLANK(E89)+ISBLANK(F89)+ISBLANK(G89) -> 0 | B89: Maneuver | C89: Counterspell | D89: (10) as interrupt, attempt to counter a spell | E89: (10) as interrupt, attempt to counter a spell. Roll Cast stat + spellcasting skill + other bonuses vs. the spellcaster's roll in place of a normal resistance check. | F89: 5 | G89: 7U,(9) | I89: 6 | M89: 6 | O89: 5
A90: =ISBLANK(B90)+ISBLANK(C90)+ISBLANK(D90)+ISBLANK(E90)+ISBLANK(F90)+ISBLANK(G90) -> 0 | B90: Maneuver | C90: Cratering Charge | D90: AoE impact on a charge | E90: (5) in addition to your charge, make a secondary melee attack at STR+2 DV against all adjacent targets, full dice pool vs. each target. ___________________ STR + 4 DV ___________________ STR + 6 DV | F90: 10/20/30 | G90: 7(R|G),(9) 14(R|G),(18) 20(R|G),(27) | K90: 6 | L90: 6 | M90: 6 | O90: 10 | P90: 30 | Q90: 60
A91: =ISBLANK(B91)+ISBLANK(C91)+ISBLANK(D91)+ISBLANK(E91)+ISBLANK(F91)+ISBLANK(G91) -> 0 | B91: Maneuver | C91: Crushing Descent | D91: Bonus for attacks made while falling | E91: Make a melee attack while falling or diving. Gain.+1 die per 10 fallen as part of the action. Capped at your BOD | F91: 20 | G91: 6(W|G),(12) | H91: 8 | K91: 8 | M91: 8 | O91: 20
A92: =ISBLANK(B92)+ISBLANK(C92)+ISBLANK(D92)+ISBLANK(E92)+ISBLANK(F92)+ISBLANK(G92) -> 0 | B92: Maneuver | C92: Dancing Weapon | D92: enchant a weapon to float and attack enemies | E92: half action, or (5) after attacking with a melee weapon. Release one held melee weapon and choose an enemy, the weapon pursues and attacks that enemy until the end of the round. The weapon acts on your turn, has a fly speed of 30' with perfect maneuverability, uses your weapon skill for its attacks (benefits from tradition match but not your agility), and deals damage as if you were wielding it. At the end of the round the weapon moves 30' towards you, dropping where it ends its movement if you do not have an open hand to grab it as a nonaction, or if it fails to reach you. | F92: 40 | G92: 12W,(24) | O92: 40
A93: =ISBLANK(B93)+ISBLANK(C93)+ISBLANK(D93)+ISBLANK(E93)+ISBLANK(F93)+ISBLANK(G93) -> 0 | B93: Maneuver | C93: Deflecting Dodge | D93: Redirect attack that missed you to adjacent valid target. | E93: Spend (5) to redirect an attack that you succesfully dodged to an adjacent valid target. The new target must resist the original attack roll, damage value and any other related effects. ______ Spend (1) | F93: 5/15 | G93: 4R,(9) 9R,(18) | K93: 4 | M93: 4 | O93: 5 | P93: 20
A94: =ISBLANK(B94)+ISBLANK(C94)+ISBLANK(D94)+ISBLANK(E94)+ISBLANK(F94)+ISBLANK(G94) -> 0 | B94: Maneuver | C94: Desert Tempest | D94: Twirl around the battlefield slicing foes as you move | E94: (10) As part of this manuever move up to your speed. You may make a single melee attack against each enemy you become adjacent to; you may not attack the same foe more than once during this manuever. _________ (5) | F94: 20/40 | G94: 16(W|R),(21) 24(W|R),(30) | H94: 14 | K94: 14 | M94: 14 | O94: 20 | P94: 60
A95: =ISBLANK(B95)+ISBLANK(C95)+ISBLANK(D95)+ISBLANK(E95)+ISBLANK(F95)+ISBLANK(G95) -> 0 | B95: Maneuver | C95: Desperate Gambit | D95: take off turn action as if previously readied | E95: (20) perform an action as an interrupt as if it were readied. _______________________ (15) | F95: 20/40 | G95: 14R,(18) 20R,(27) | K95: 12 | M95: 12 | O95: 20 | P95: 60
A96: =ISBLANK(B96)+ISBLANK(C96)+ISBLANK(D96)+ISBLANK(E96)+ISBLANK(F96)+ISBLANK(G96) -> 0 | B96: Maneuver | C96: Devour Essence | D96: Absorb some energy from a dying / recently slain foe | E96: full action, touch, targets a dead or dying creature. A dying creature rolls BOD vs. WIL to resist, failure or tie results in its death. This maneuver automatically succeeds against a target that has been dead for up to (YOUR BOD) rounds, on more rounds than that no effect. Heal 1 stamina, if at full stamina heal 1 health, if at full health and stamina, gain 1 temporary point of health/stam that is lost first. This point lasts for (Creature's BOD) hours. | F96: 10 | G96: 2B,2(B|G),(9) | J96: 3 | L96: 3 | M96: 6 | O96: 10
A97: =ISBLANK(B97)+ISBLANK(C97)+ISBLANK(D97)+ISBLANK(E97)+ISBLANK(F97)+ISBLANK(G97) -> 0 | B97: Maneuver | C97: Discorporation | D97: Avert death, reform later | E97: Spend all your LUK when you would die. If your spent LUK exceeds the damage you died by you discorporate and return next (time of day) at full health at a nearby safe location. | F97: 20 | G97: 7B,(30) | O97: 20
A98: =ISBLANK(B98)+ISBLANK(C98)+ISBLANK(D98)+ISBLANK(E98)+ISBLANK(F98)+ISBLANK(G98) -> 0 | B98: Maneuver | C98: Disperse into Mist | D98: Disperse into mist in response to taking a blow | E98: Spend (10) as a nonaction after taking damage from an attack. You disperse into mist and are untargetable until the start of your next turn, or the start of the next round (your choice). While dispersed you cannot take actions or affect other creatures, objects, or terrain (you may still move). | F98: 30 | G98: 5G,(21) | O98: 30
A99: =ISBLANK(B99)+ISBLANK(C99)+ISBLANK(D99)+ISBLANK(E99)+ISBLANK(F99)+ISBLANK(G99) -> 0 | B99: Maneuver | C99: Distant Echoes | D99: Launch projectile, sense general surroundings near projectile | E99: Extra action - you gain blindsense 10ft around the impact point of the projectile until the end of the turn half action - until the end of next round. ____________ Extra action - until end of round half action - until end of next round | F99: 15/25 | G99: 6(W|G),(12) 10(W|G),(21) | O99: 15 | P99: 40
A100: =ISBLANK(B100)+ISBLANK(C100)+ISBLANK(D100)+ISBLANK(E100)+ISBLANK(F100)+ISBLANK(G100) -> 0 | B100: Maneuver | C100: Divert Attention | D100: half action: roll to stealth as if you had moved | E100: half action: you may roll to stealth as if you had moved. This ability does not fulfill any other conditions required for stealthing. _______________ extra action | F100: 10/60 | G100: 3G,(12) 7G,(27) | O100: 10 | P100: 70
...

Sheet NCT
A1: ver 0.53 | C1: Racials | D1: CP | G1: RANK | I1: CP | K1: Dicepool | N1: Current | O1: +Max
A2: BOD | B2: 1 | C2: 1 | D2: =(B2^2+B2-2)*2.5 - 10*C2 -> -10 | E2: B | F2: ATHLETICS | G2: 0 | I2: =IF(G2>0,(G2^2+G2+2)*2.5,0) -> 0 | L2: HP | M2: =16+B2+O2 -> 17 | N2: 9 | O2: 0
A3: AGI | B3: 1 | C3: 1 | D3: =(B3^2+B3-2)*2.5 - 10*C3 -> -10 | E3: A | F3: Strongman | G3: 0 | H3: S | I3: =IF(OR($I$2>0,G3=0),0,(G3^2+G3+2)) -> 0 | J3: =H3 -> S | K3: =OFFSET($B$1, MATCH(H3,$E$2:$E$9,0),0)+IF($G$2>0,$G$2+MIN(CEILING($B$13/2,1),$G$2),G3+IF(G3=0,-1,0)+MIN(CEILING($B$13/2,1),G3)) -> 0 | L3: STAM | M3: =16+B6+O3 -> 17 | N3: 9 | O3: 0
A4: REA | B4: 1 | D4: =(B4^2+B4-2)*2.5 - 10*C4 -> 0 | E4: R | F4: Gymnastics | G4: 0 | H4: A | I4: =IF(OR($I$2>0,G4=0),0,(G4^2+G4+2)) -> 0 | J4: =H4 -> A | K4: =OFFSET($B$1, MATCH(H4,$E$2:$E$9,0),0)+IF($G$2>0,$G$2+MIN(CEILING($B$13/2,1),$G$2),G4+IF(G4=0,-1,0)+MIN(CEILING($B$13/2,1),G4)) -> 0 | L4: DRAIN | M4: =16+OFFSET($B$1, MATCH(H22,$E$2:$E$9,0),0)+O4 -> 17 | N4: 9 | O4: 0
A5: STR | B5: 1 | D5: =(B5^2+B5-2)*2.5 - 10*C5 -> 0 | E5: S | F5: Marathoner | G5: 0 | H5: B | I5: =IF(OR($I$2>0,G5=0),0,(G5^2+G5+2)) -> 0 | J5: =H5 -> B | K5: =OFFSET($B$1, MATCH(H5,$E$2:$E$9,0),0)+IF($G$2>0,$G$2+MIN(CEILING($B$13/2,1),$G$2),G5+IF(G5=0,-1,0)+MIN(CEILING($B$13/2,1),G5)) -> 0 | L5: LUK | M5: =B10 -> 1 | N5: 1
A6: WIL | B6: 1 | D6: =(B6^2+B6-2)*2.5 - 10*C6 -> 0 | E6: W | F6: Traversal | G6: 0 | H6: R | I6: =IF(OR($I$2>0,G6=0),0,(G6^2+G6+2)) -> 0 | J6: =H6 -> R | K6: =OFFSET($B$1, MATCH(H6,$E$2:$E$9,0),0)+IF($G$2>0,$G$2+MIN(CEILING($B$13/2,1),$G$2),G6+IF(G6=0,-1,0)+MIN(CEILING($B$13/2,1),G6)) -> 0 | L6: DV Threshold | M6: =B2 -> 1 | N6: MISC
A7: INT | B7: 1 | D7: =(B7^2+B7-2)*2.5 - 10*C7 -> 0 | E7: I | F7: SURVIVAL | G7: 0 | I7: =IF(G7>0,(G7^2+G7+2)*2.5,0) -> 0 | L7: ARMOR SOAK | M7: =CEILING(((2-1*(L11="Light Armor"))*B2+B8)/2,1)+N7 -> 2
A8: LOG | B8: 1 | D8: =(B8^2+B8-2)*2.5 - 10*C8 -> 0 | E8: L | F8: Navigation | G8: 0 | H8: I | I8: =IF(OR($I$7>0,G8=0),0,(G8^2+G8+2)) -> 0 | J8: =H8 -> I | K8: =OFFSET($B$1, MATCH(H8,$E$2:$E$9,0),0)+IF($G$7>0,$G$7+MIN(CEILING($B$13/2,1),$G$7),G8+IF(G8=0,-1,0)+MIN(CEILING($B$13/2,1),G8)) -> 0 | L8: PHYS SOAK | M8: =CEILING((B3+2*B5)/2,1)+N8 -> 2
A9: CHA | B9: 1 | D9: =(B9^2+B9-2)*2.5 - 10*C9 -> 0 | E9: C | F9: Survival | G9: 0 | H9: W | I9: =IF(OR($I$7>0,G9=0),0,(G9^2+G9+2)) -> 0 | J9: =H9 -> W | K9: =OFFSET($B$1, MATCH(H9,$E$2:$E$9,0),0)+IF($G$7>0,$G$7+MIN(CEILING($B$13/2,1),$G$7),G9+IF(G9=0,-1,0)+MIN(CEILING($B$13/2,1),G9)) -> 0 | L9: MENTAL SOAK | M9: =CEILING((2*B6+B9)/2,1)+N9 -> 2
A10: LUK | B10: 1 | D10: =(B10^2+B10-2)*2.5 - 10*C10 -> 0 | F10: Medicine | G10: 0 | H10: L | I10: =IF(OR($I$7>0,G10=0),0,(G10^2+G10+2)) -> 0 | J10: =H10 -> L | K10: =OFFSET($B$1, MATCH(H10,$E$2:$E$9,0),0)+IF($G$7>0,$G$7+MIN(CEILING($B$13/2,1),$G$7),G10+IF(G10=0,-1,0)+MIN(CEILING($B$13/2,1),G10)) -> 0 | L10: DRAIN SOAK P | M10: =2*B6+N10 -> 2
A11: CAST STAT | B11: LOG | F11: Animal Handling | G11: 0 | H11: I | I11: =IF(OR($I$7>0,G11=0),0,(G11^2+G11+2)) -> 0 | J11: =H11 -> I | K11: =OFFSET($B$1, MATCH(H11,$E$2:$E$9,0),0)+IF($G$7>0,$G$7+MIN(CEILING($B$13/2,1),$G$7),G11+IF(G11=0,-1,0)+MIN(CEILING($B$13/2,1),G11)) -> 0 | L11: Normal Armor | M11: Passive | N11: Active | O11: MISC
F12: INFLUENCE | G12: 0 | I12: =IF(G12>0,(G12^2+G12+2)*2.5,0) -> 0 | L12: Dodge | M12: =B7+B4 -> 2 | N12: =M12+G26+MIN(G26,CEILING(B13/2,1))+O12+(G26*(L11="Light Armor")) -> 2
A13: TRAD | B13: 1 | C13: =(B13^2+7*B13-8)*2.5 -> 0 | F13: Con | G13: 0 | H13: C | I13: =IF(OR($I$12>0,G13=0),0,(G13^2+G13+2)) -> 0 | J13: =H13 -> C | K13: =OFFSET($B$1, MATCH(H13,$E$2:$E$9,0),0)+IF($G$12>0,$G$12+MIN(CEILING($B$13/2,1),$G$12),G13+IF(G13=0,-1,0)+MIN(CEILING($B$13/2,1),G13)) -> 0 | L13: Parry | M13: - | N13: =M12+G24+MIN(CEILING(B13/2,1),G24)+O13+N30 -> 3
A14: W | B14: 0 | F14: Insight | G14: 0 | H14: I | I14: =IF(OR($I$12>0,G14=0),0,(G14^2+G14+2)) -> 0 | J14: =H14 -> I | K14: =OFFSET($B$1, MATCH(H14,$E$2:$E$9,0),0)+IF($G$12>0,$G$12+MIN(CEILING($B$13/2,1),$G$12),G14+IF(G14=0,-1,0)+MIN(CEILING($B$13/2,1),G14)) -> 0 | L14: Block | M14: - | N14: =M12+G24+MIN(CEILING(B13/2,1),G24)+O14+N34 -> 2
A15: U | B15: 0 | F15: Intimidation | G15: 0 | H15: C | I15: =IF(OR($I$12>0,G15=0),0,(G15^2+G15+2)) -> 0 | J15: =H15 -> C | K15: =OFFSET($B$1, MATCH(H15,$E$2:$E$9,0),0)+IF($G$12>0,$G$12+MIN(CEILING($B$13/2,1),$G$12),G15+IF(G15=0,-1,0)+MIN(CEILING($B$13/2,1),G15)) -> 0 | L15: Physical | M15: =B2+B3 -> 2 | N15: =M15+G27+MIN(CEILING(B13/2,1),G27)+O15 -> 2
A16: B | B16: 0 | F16: Negotiation | G16: 0 | H16: C | I16: =IF(OR($I$12>0,G16=0),0,(G16^2+G16+2)) -> 0 | J16: =H16 -> C | K16: =OFFSET($B$1, MATCH(H16,$E$2:$E$9,0),0)+IF($G$12>0,$G$12+MIN(CEILING($B$13/2,1),$G$12),G16+IF(G16=0,-1,0)+MIN(CEILING($B$13/2,1),G16)) -> 0 | L16: Mental | M16: =B6+B9 -> 2 | N16: =M16+G27+MIN(CEILING(B13/2,1),G27)+O16 -> 2
A17: R | B17: 0 | F17: SUBTERFUGE | G17: 0 | I17: =IF(G17>0,(G17^2+G17+2)*2.5,0) -> 0 | M17: 1 | N17: 2 | O17: 3
A18: G | B18: 0 | F18: Disguise | G18: 0 | H18: I | I18: =IF(OR($I$17>0,G18=0),0,(G18^2+G18+2)) -> 0 | J18: =H18 -> I | K18: =OFFSET($B$1, MATCH(H18,$E$2:$E$9,0),0)+IF($G$17>0,$G$17+MIN(CEILING($B$13/2,1),$G$17),G18+IF(G18=0,-1,0)+MIN(CEILING($B$13/2,1),G18)) -> 0 | M18: Melee | N18: Melee | O18: Melee
D19: Know discount | F19: Stealth | G19: 0 | H19: A | I19: =IF(OR($I$17>0,G19=0),0,(G19^2+G19+2)) -> 0 | J19: =H19 -> A | K19: =OFFSET($B$1, MATCH(H19,$E$2:$E$9,0),0)+IF($G$17>0,$G$17+MIN(CEILING($B$13/2,1),$G$17),G19+IF(G19=0,-1,0)+MIN(CEILING($B$13/2,1),G19)) -> 0 | L19: Name
A20: BP Current | B20: =SUM(D2:D10)+SUM(C13:C18)+SUM(I2:I36)+SUM(G41:G125)-MIN(SUM(I28:I36),D20) -> 20 | D20: =(B8+B7)*10 -> 20 | F20: Legerdemain | G20: 0 | H20: A | I20: =IF(OR($I$17>0,G20=0),0,(G20^2+G20+2)) -> 0 | J20: =H20 -> A | K20: =OFFSET($B$1, MATCH(H20,$E$2:$E$9,0),0)+IF($G$17>0,$G$17+MIN(CEILING($B$13/2,1),$G$17),G20+IF(G20=0,-1,0)+MIN(CEILING($B$13/2,1),G20)) -> 0 | L20: Weapon | M20: Light | N20: 1H | O20: 2H
A21: BP Budget | B21: 1620 | F21: Thievery | G21: 0 | H21: A | I21: =IF(OR($I$17>0,G21=0),0,(G21^2+G21+2)) -> 0 | J21: =H21 -> A | K21: =OFFSET($B$1, MATCH(H21,$E$2:$E$9,0),0)+IF($G$17>0,$G$17+MIN(CEILING($B$13/2,1),$G$17),G21+IF(G21=0,-1,0)+MIN(CEILING($B$13/2,1),G21)) -> 0 | L21: Power | M21: 4 | N21: 4 | O21: 6
F22: Spellcasting | G22: 0 | H22: =OFFSET($E$1, MATCH($B$11,$A$2:$A$10,0),0) -> L | I22: =IF(G22>0,(G22^2+G22+2),0) -> 0 | J22: =H22 -> L | K22: =OFFSET($B$1, MATCH(H22,$E$2:$E$9,0),0)+G22+MIN(CEILING($B$13/2,1),G22) -> 1 | L22: Reach | M22: =IF(M$18="Melee", OFFSET($B$24,0,MATCH(M$20,$C$23:$E$23,0))-M$21,0) -> 1 | N22: =IF(N$18="Melee", OFFSET($B$24,0,MATCH(N$20,$C$23:$E$23,0))-N$21,0) -> 2 | O22: =IF(O$18="Melee", OFFSET($B$24,0,MATCH(O$20,$C$23:$E$23,0))-O$21,0) -> 2
C23: Light | D23: 1H | E23: 2H | F23: Perceive Magic | G23: 0 | H23: =OFFSET($E$1, MATCH($B$11,$A$2:$A$10,0),0) -> L | I23: =IF(G23>0,(G23^2+G23+2),0) -> 0 | J23: =H23 -> L | K23: =OFFSET($B$1, MATCH(H23,$E$2:$E$9,0),0)+G23+MIN(CEILING($B$13/2,1),G23) -> 1 | L23: DV | M23: =M$21+$B$5 -> 5 | N23: =N$21+$B$5 -> 5 | O23: =O$21+$B$5 -> 7
C24: 5 | D24: 6 | E24: 8 | F24: (weapon skill) | G24: 0 | H24: A | I24: =IF(G24>0,(G24^2+G24+2),0) -> 0 | J24: =H24 -> A | K24: =OFFSET($B$1, MATCH(H24,$E$2:$E$9,0),0)+G24+MIN(CEILING($B$13/2,1),G24) -> 1 | L24: Dicepool | M24: =$K$24+M$22+IF(AND(M$20="2H",M$25="Buckler"),-2,0) -> 2 | N24: =$K$24+N$22+IF(AND(N$20="2H",N$25="Buckler"),-2,0) -> 3 | O24: =$K$24+O$22+IF(AND(O$20="2H",O$25="Buckler"),-2,0) -> 3
F25: Perception | G25: 0 | H25: I | I25: =IF(G25>0,(G25^2+G25+2),0) -> 0 | J25: =H25 -> I | K25: =OFFSET($B$1, MATCH(H25,$E$2:$E$9,0),0)+G25+MIN(CEILING($B$13/2,1),G25) -> 1 | L25: Shield | M25: None | N25: None | O25: None
F26: Dodge | G26: 0 | H26: N/A | I26: =IF(G26>0,(G26^2+G26+2),0) -> 0 | L26: Shield Bonus | M26: =OFFSET($D$30,MATCH(M$25,$D$26:$D$31,0),0) -> 0 | N26: =OFFSET($D$30,MATCH(N$25,$D$26:$D$31,0),0) -> 0 | O26: =OFFSET($D$30,MATCH(O$25,$D$26:$D$31,0),0) -> 0
C27: None | D27: None | E27: None | F27: Perserverence | G27: 0 | H27: N/A | I27: =IF(G27>0,(G27^2+G27+2),0) -> 0 | M27: Weapon # | N27: 1
C28: Buckler | D28: Buckler | E28: Buckler | F28: Knowledge | G28: 0 | H28: =J28 -> L | I28: =IF(G28>0,(G28^2+G28+2),0)/2 -> 0 | J28: L | K28: =OFFSET($B$1, MATCH(H28,$E$2:$E$9,0),0)+G28+MIN(CEILING($B$13/2,1),G28) -> 1 | M28: Weapon | N28: =OFFSET(L20,0,$N$27) -> Light | O28: X foot reach
C29: Medium | D29: Medium | F29: Knowledge | G29: 0 | H29: =J29 -> L | I29: =IF(G29>0,(G29^2+G29+2),0)/2 -> 0 | J29: L | K29: =OFFSET($B$1, MATCH(H29,$E$2:$E$9,0),0)+G29+MIN(CEILING($B$13/2,1),G29) -> 1 | M29: Power | N29: =OFFSET(L21,0,$N$27)-2*(O33<>"None") -> 4 | O29: =MAX(0,FLOOR(N30/2,1)-1)*5+5 -> 5
C30: Heavy | D30: Heavy | F30: Knowledge | G30: 0 | H30: =J30 -> L | I30: =IF(G30>0,(G30^2+G30+2),0)/2 -> 0 | J30: L | K30: =OFFSET($B$1, MATCH(H30,$E$2:$E$9,0),0)+G30+MIN(CEILING($B$13/2,1),G30) -> 1 | M30: Reach | N30: =OFFSET(L22,0,$N$27)+O31 -> 1 | O30: Reach Bonus
C31: Tower | D31: Tower | F31: Knowledge | G31: 0 | H31: =J31 -> L | I31: =IF(G31>0,(G31^2+G31+2),0)/2 -> 0 | J31: L | K31: =OFFSET($B$1, MATCH(H31,$E$2:$E$9,0),0)+G31+MIN(CEILING($B$13/2,1),G31) -> 1 | M31: DV | N31: =OFFSET(L23,0,$N$27) -> 5 | O31: 0
C32: =OFFSET(B27,0,MATCH($M$20,$C$23:$E$23,0)) -> None | D32: 0 | F32: Knowledge | G32: 0 | H32: =J32 -> L | I32: =IF(G32>0,(G32^2+G32+2),0)/2 -> 0 | J32: L | K32: =OFFSET($B$1, MATCH(H32,$E$2:$E$9,0),0)+G32+MIN(CEILING($B$13/2,1),G32) -> 1 | M32: Dicepool | N32: =OFFSET(L24,0,$N$27) -> 2 | O32: ELEMENT
C33: =OFFSET(B28,0,MATCH($M$20,$C$23:$E$23,0)) -> Buckler | D33: 1 | F33: Knowledge | G33: 0 | H33: =J33 -> L | I33: =IF(G33>0,(G33^2+G33+2),0)/2 -> 0 | J33: L | K33: =OFFSET($B$1, MATCH(H33,$E$2:$E$9,0),0)+G33+MIN(CEILING($B$13/2,1),G33) -> 1 | M33: Shield | N33: =OFFSET(L25,0,$N$27) -> None | O33: None
C34: =OFFSET(B29,0,MATCH($M$20,$C$23:$E$23,0)) -> Medium | D34: 4 | F34: Knowledge | G34: 0 | H34: =J34 -> L | I34: =IF(G34>0,(G34^2+G34+2),0)/2 -> 0 | J34: L | K34: =OFFSET($B$1, MATCH(H34,$E$2:$E$9,0),0)+G34+MIN(CEILING($B$13/2,1),G34) -> 1 | M34: Shield Bonus | N34: =OFFSET(L26,0,$N$27) -> 0
C35: =OFFSET(B30,0,MATCH($M$20,$C$23:$E$23,0)) -> Heavy | D35: 5 | F35: Knowledge | G35: 0 | H35: =J35 -> L | I35: =IF(G35>0,(G35^2+G35+2),0)/2 -> 0 | J35: L | K35: =OFFSET($B$1, MATCH(H35,$E$2:$E$9,0),0)+G35+MIN(CEILING($B$13/2,1),G35) -> 1
C36: =OFFSET(B31,0,MATCH($M$20,$C$23:$E$23,0)) -> Tower | D36: 7 | F36: Knowledge | G36: 0 | H36: =J36 -> L | I36: =IF(G36>0,(G36^2+G36+2),0)/2 -> 0 | J36: L | K36: =OFFSET($B$1, MATCH(H36,$E$2:$E$9,0),0)+G36+MIN(CEILING($B$13/2,1),G36) -> 1
B39: Abilities
A40: Rank | B40: Name | G40: Cost | J40: Affinity
A41: 1 | B41: Break Resolve | G41: =IFERROR(OFFSET(Abilities!$N$1,MATCH(B41,Abilities!C:C,0)-1,A41),0) -> 40 | J41: =OFFSET(Abilities!$N$1,MATCH(B41,Abilities!C:C,0)-1,-7) -> ??,(27) | K41: =OFFSET(Abilities!$N$1,MATCH(B41,Abilities!C:C,0)-1,-12) -> Maneuver | L41: =OFFSET(Abilities!$N$1,MATCH(B41,Abilities!C:C,0)-1,-9) -> (5) When you are the only target of an enemy's action. Make an Intimidation attempt against the enemy. If this puts the enemy to 3 or more fear stacks negate the enemy's action.
A42: 1 | B42: Ability Name | G42: =IFERROR(OFFSET(Abilities!$N$1,MATCH(B42,Abilities!C:C,0)-1,A42),0) -> R1 | J42: =OFFSET(Abilities!$N$1,MATCH(B42,Abilities!C:C,0)-1,-7) -> Affinity req | K42: =OFFSET(Abilities!$N$1,MATCH(B42,Abilities!C:C,0)-1,-12) -> Category | L42: =OFFSET(Abilities!$N$1,MATCH(B42,Abilities!C:C,0)-1,-9) -> Rules Text
A43: 1 | B43: Ability Name | G43: =IFERROR(OFFSET(Abilities!$N$1,MATCH(B43,Abilities!C:C,0)-1,A43),0) -> R1 | J43: =OFFSET(Abilities!$N$1,MATCH(B43,Abilities!C:C,0)-1,-7) -> Affinity req | K43: =OFFSET(Abilities!$N$1,MATCH(B43,Abilities!C:C,0)-1,-12) -> Category | L43: =OFFSET(Abilities!$N$1,MATCH(B43,Abilities!C:C,0)-1,-9) -> Rules Text
A44: 1 | B44: Ability Name | G44: =IFERROR(OFFSET(Abilities!$N$1,MATCH(B44,Abilities!C:C,0)-1,A44),0) -> R1 | J44: =OFFSET(Abilities!$N$1,MATCH(B44,Abilities!C:C,0)-1,-7) -> Affinity req | K44: =OFFSET(Abilities!$N$1,MATCH(B44,Abilities!C:C,0)-1,-12) -> Category | L44: =OFFSET(Abilities!$N$1,MATCH(B44,Abilities!C:C,0)-1,-9) -> Rules Text
A45: 1 | B45: Ability Name | G45: =IFERROR(OFFSET(Abilities!$N$1,MATCH(B45,Abilities!C:C,0)-1,A45),0) -> R1 | J45: =OFFSET(Abilities!$N$1,MATCH(B45,Abilities!C:C,0)-1,-7) -> Affinity req | K45: =OFFSET(Abilities!$N$1,MATCH(B45,Abilities!C:C,0)-1,-12) -> Category | L45: =OFFSET(Abilities!$N$1,MATCH(B45,Abilities!C:C,0)-1,-9) -> Rules Text
A46: 1 | B46: Ability Name | G46: =IFERROR(OFFSET(Abilities!$N$1,MATCH(B46,Abilities!C:C,0)-1,A46),0) -> R1 | J46: =OFFSET(Abilities!$N$1,MATCH(B46,Abilities!C:C,0)-1,-7) -> Affinity req | K46: =OFFSET(Abilities!$N$1,MATCH(B46,Abilities!C:C,0)-1,-12) -> Category | L46: =OFFSET(Abilities!$N$1,MATCH(B46,Abilities!C:C,0)-1,-9) -> Rules Text
A47: 1 | B47: Ability Name | G47: =IFERROR(OFFSET(Abilities!$N$1,MATCH(B47,Abilities!C:C,0)-1,A47),0) -> R1 | J47: =OFFSET(Abilities!$N$1,MATCH(B47,Abilities!C:C,0)-1,-7) -> Affinity req | K47: =OFFSET(Abilities!$N$1,MATCH(B47,Abilities!C:C,0)-1,-12) -> Category | L47: =OFFSET(Abilities!$N$1,MATCH(B47,Abilities!C:C,0)-1,-9) -> Rules Text
A48: 1 | B48: Ability Name | G48: =IFERROR(OFFSET(Abilities!$N$1,MATCH(B48,Abilities!C:C,0)-1,A48),0) -> R1 | J48: =OFFSET(Abilities!$N$1,MATCH(B48,Abilities!C:C,0)-1,-7) -> Affinity req | K48: =OFFSET(Abilities!$N$1,MATCH(B48,Abilities!C:C,0)-1,-12) -> Category | L48: =OFFSET(Abilities!$N$1,MATCH(B48,Abilities!C:C,0)-1,-9) -> Rules Text
A49: 1 | B49: Ability Name | G49: =IFERROR(OFFSET(Abilities!$N$1,MATCH(B49,Abilities!C:C,0)-1,A49),0) -> R1 | J49: =OFFSET(Abilities!$N$1,MATCH(B49,Abilities!C:C,0)-1,-7) -> Affinity req | K49: =OFFSET(Abilities!$N$1,MATCH(B49,Abilities!C:C,0)-1,-12) -> Category | L49: =OFFSET(Abilities!$N$1,MATCH(B49,Abilities!C:C,0)-1,-9) -> Rules Text
A50: 1 | B50: Ability Name | G50: =IFERROR(OFFSET(Abilities!$N$1,MATCH(B50,Abilities!C:C,0)-1,A50),0) -> R1 | J50: =OFFSET(Abilities!$N$1,MATCH(B50,Abilities!C:C,0)-1,-7) -> Affinity req | K50: =OFFSET(Abilities!$N$1,MATCH(B50,Abilities!C:C,0)-1,-12) -> Category | L50: =OFFSET(Abilities!$N$1,MATCH(B50,Abilities!C:C,0)-1,-9) -> Rules Text
A51: 1 | B51: Ability Name | G51: =IFERROR(OFFSET(Abilities!$N$1,MATCH(B51,Abilities!C:C,0)-1,A51),0) -> R1 | J51: =OFFSET(Abilities!$N$1,MATCH(B51,Abilities!C:C,0)-1,-7) -> Affinity req | K51: =OFFSET(Abilities!$N$1,MATCH(B51,Abilities!C:C,0)-1,-12) -> Category | L51: =OFFSET(Abilities!$N$1,MATCH(B51,Abilities!C:C,0)-1,-9) -> Rules Text
A52: 1 | B52: Ability Name | G52: =IFERROR(OFFSET(Abilities!$N$1,MATCH(B52,Abilities!C:C,0)-1,A52),0) -> R1 | J52: =OFFSET(Abilities!$N$1,MATCH(B52,Abilities!C:C,0)-1,-7) -> Affinity req | K52: =OFFSET(Abilities!$N$1,MATCH(B52,Abilities!C:C,0)-1,-12) -> Category | L52: =OFFSET(Abilities!$N$1,MATCH(B52,Abilities!C:C,0)-1,-9) -> Rules Text
... A125: 1 | B125: Ability Name | G125: =IFERROR(OFFSET(Abilities!$N$1,MATCH(B125,Abilities!C:C,0)-1,A125),0) -> R1 | J125: =OFFSET(Abilities!$N$1,MATCH(B125,Abilities!C:C,0)-1,-7) -> Affinity req | K125: =OFFSET(Abilities!$N$1,MATCH(B125,Abilities!C:C,0)-1,-12) -> Category | L125: =OFFSET(Abilities!$N$1,MATCH(B125,Abilities!C:C,0)-1,-9) -> Rules Text

Sheet Iobia
C1: Racials | D1: CP | G1: RANK | I1: CP | K1: Dicepool | N1: Current | O1: +Max | Q1: To cure being starblinded - flower from the tallest mountain that has seen every sunrise of the year Sunmage has heard about a valley that has not seen rain, cloudless valley. Infer, giant beast nesting grounds (Kaiju) Druidess Lands - druidess, was helped over demon and dumb idiot dude. Iobia has crafted a picture good enough for a sovineirg War Graveyard - Magic Gophers, made fake lord of bones to harrange travelers, shoot fireballs. Fortress westward, skeletons all headless Ziggurat picture - sickness when traveling, boggy area. Indigenous populations. Big giant forest monsters. Ancient Undead City- dust devils, blue chasing green Icey North - ice worms, yetis, dire wolves Kaiju Turtle - Gexians are harvesting his bone marrow, ask Ferrofist for ship diagrams, engine room blow ups, maybe he want to help? Smith murder - coated in molten - Ferrofist - Smith was gexian. What is gexias larger puzzle piece? (gexian outposts could be friendly) Flying ship - Find someone that can inform us better about using power sources Jalguez Tablet - Find someone that may know more about duplicating tablet pieces (find a sage/expert at a college devoted to study) - when more tablets are near (or meteor) they amplify/lash out, also when stored they build up energy. lash outs turn surrounding stuff tentacle Shimmering Reach MAY be finite Merchant Sons - lost merchant fleet carrying fat loot, either blown into Gexia or into the Reach Meteor Quest - Ice cave, meteor was taken already. Big curved 2 handed sword with shark teeth on the hilt, 3 adventurers (one tall one, one with the sword, one using magic)
A2: BOD | B2: 7 | C2: 1 | D2: =(B2^2+B2-2)*2.5 - 10*C2 -> 125 | E2: B | F2: ATHLETICS | G2: 1 | I2: =IF(G2>0,(G2^2+G2+2)*2.5,0) -> 10 | L2: HP | M2: =16+B2+O2 -> 23 | N2: 21 | O2: 0
A3: AGI | B3: 2 | C3: 1 | D3: =(B3^2+B3-2)*2.5 - 10*C3 -> 0 | E3: A | F3: Strongman | G3: 0 | H3: S | I3: =IF(OR($I$2>0,G3=0),0,(G3^2+G3+2)) -> 0 | J3: =H3 -> S | K3: =OFFSET($B$1, MATCH(H3,$E$2:$E$9,0),0)+IF($G$2>0,$G$2+MIN(CEILING($B$13/2,1),$G$2),G3+IF(G3=0,-1,0)+MIN(CEILING($B$13/2,1),G3)) -> 4 | L3: STAM | M3: =16+B6+O3 -> 24 | N3: 18 | O3: 0
A4: REA | B4: 5 | D4: =(B4^2+B4-2)*2.5 - 10*C4 -> 70 | E4: R | F4: Gymnastics | G4: 0 | H4: A | I4: =IF(OR($I$2>0,G4=0),0,(G4^2+G4+2)) -> 0 | J4: =H4 -> A | K4: =OFFSET($B$1, MATCH(H4,$E$2:$E$9,0),0)+IF($G$2>0,$G$2+MIN(CEILING($B$13/2,1),$G$2),G4+IF(G4=0,-1,0)+MIN(CEILING($B$13/2,1),G4)) -> 4 | L4: DRAIN | M4: =16+OFFSET($B$1, MATCH(H22,$E$2:$E$9,0),0)+O4 -> 25 | N4: 21 | O4: 0
A5: STR | B5: 2 | D5: =(B5^2+B5-2)*2.5 - 10*C5 -> 10 | E5: S | F5: Marathoner | G5: 0 | H5: B | I5: =IF(OR($I$2>0,G5=0),0,(G5^2+G5+2)) -> 0 | J5: =H5 -> B | K5: =OFFSET($B$1, MATCH(H5,$E$2:$E$9,0),0)+IF($G$2>0,$G$2+MIN(CEILING($B$13/2,1),$G$2),G5+IF(G5=0,-1,0)+MIN(CEILING($B$13/2,1),G5)) -> 9 | L5: LUK | M5: =B10 -> 5 | N5: 4
A6: WIL | B6: 8 | D6: =(B6^2+B6-2)*2.5 - 10*C6 -> 175 | E6: W | F6: Traversal | G6: 0 | H6: R | I6: =IF(OR($I$2>0,G6=0),0,(G6^2+G6+2)) -> 0 | J6: =H6 -> R | K6: =OFFSET($B$1, MATCH(H6,$E$2:$E$9,0),0)+IF($G$2>0,$G$2+MIN(CEILING($B$13/2,1),$G$2),G6+IF(G6=0,-1,0)+MIN(CEILING($B$13/2,1),G6)) -> 7 | L6: DV Threshold | M6: =B2 -> 7 | N6: MISC
A7: INT | B7: 9 | D7: =(B7^2+B7-2)*2.5 - 10*C7 -> 220 | E7: I | F7: SURVIVAL | G7: 0 | I7: =IF(G7>0,(G7^2+G7+2)*2.5,0) -> 0 | L7: ARMOR SOAK | M7: =CEILING(((2-1*(L11="Light Armor"))*B2+B8)/2,1)+N7 -> 9
A8: LOG | B8: 3 | D8: =(B8^2+B8-2)*2.5 - 10*C8 -> 25 | E8: L | F8: Navigation | G8: 1 | H8: I | I8: =IF(OR($I$7>0,G8=0),0,(G8^2+G8+2)) -> 4 | J8: =H8 -> I | K8: =OFFSET($B$1, MATCH(H8,$E$2:$E$9,0),0)+IF($G$7>0,$G$7+MIN(CEILING($B$13/2,1),$G$7),G8+IF(G8=0,-1,0)+MIN(CEILING($B$13/2,1),G8)) -> 11 | L8: PHYS SOAK | M8: =CEILING((B3+2*B5)/2,1)+N8 -> 3
A9: CHA | B9: 2 | D9: =(B9^2+B9-2)*2.5 - 10*C9 -> 10 | E9: C | F9: Survival | G9: 0 | H9: W | I9: =IF(OR($I$7>0,G9=0),0,(G9^2+G9+2)) -> 0 | J9: =H9 -> W | K9: =OFFSET($B$1, MATCH(H9,$E$2:$E$9,0),0)+IF($G$7>0,$G$7+MIN(CEILING($B$13/2,1),$G$7),G9+IF(G9=0,-1,0)+MIN(CEILING($B$13/2,1),G9)) -> 7 | L9: MENTAL SOAK | M9: =CEILING((2*B6+B9)/2,1)+N9 -> 9
A10: LUK | B10: 5 | D10: =(B10^2+B10-2)*2.5 - 10*C10 -> 70 | F10: Medicine | G10: 1 | H10: L | I10: =IF(OR($I$7>0,G10=0),0,(G10^2+G10+2)) -> 4 | J10: =H10 -> L | K10: =OFFSET($B$1, MATCH(H10,$E$2:$E$9,0),0)+IF($G$7>0,$G$7+MIN(CEILING($B$13/2,1),$G$7),G10+IF(G10=0,-1,0)+MIN(CEILING($B$13/2,1),G10)) -> 5 | L10: DRAIN SOAK P | M10: =2*B6+N10 -> 16
A11: CAST STAT | B11: INT | F11: Animal Handling | G11: 0 | H11: I | I11: =IF(OR($I$7>0,G11=0),0,(G11^2+G11+2)) -> 0 | J11: =H11 -> I | K11: =OFFSET($B$1, MATCH(H11,$E$2:$E$9,0),0)+IF($G$7>0,$G$7+MIN(CEILING($B$13/2,1),$G$7),G11+IF(G11=0,-1,0)+MIN(CEILING($B$13/2,1),G11)) -> 8 | L11: Normal Armor | M11: Passive | N11: Active | O11: MISC | Q11: Sketches Large giant albino finned sea monster, 4 part mouth, dives deep and then rises, using its maw to vortex massive amounts of water consuming the flesh inside Herald of fire and ash demon skull Charcoal relief of tablet piece Souviner picture of Daemon, Northerner, and Druid with the well of souls Oil painting of Petradonis - rat city, huge towering white walls surrounded by field of demons with a shimmering wall all around Bracelet of Teeth Death Mage Tooth Ash Demon Tooth Dire Wolf Tooth Statue of petrified tentacle rat (both the tablet relief made it turn green with some tentacles and dark damage amplified it) then silas petrified it
F12: INFLUENCE | G12: 0 | I12: =IF(G12>0,(G12^2+G12+2)*2.5,0) -> 0 | L12: Dodge | M12: =B7+B4 -> 14 | N12: =M12+G26+MIN(G26,CEILING(B13/2,1))+O12+(G26*(L11="Light Armor")) -> 26
A13: TRAD | B13: 10 | C13: =(B13^2+7*B13-8)*2.5 -> 405 | F13: Con | G13: 2 | H13: C | I13: =IF(OR($I$12>0,G13=0),0,(G13^2+G13+2)) -> 8 | J13: =H13 -> C | K13: =OFFSET($B$1, MATCH(H13,$E$2:$E$9,0),0)+IF($G$12>0,$G$12+MIN(CEILING($B$13/2,1),$G$12),G13+IF(G13=0,-1,0)+MIN(CEILING($B$13/2,1),G13)) -> 6 | L13: Parry | M13: - | N13: =M12+G24+MIN(CEILING(B13/2,1),G24)+O13+N30 -> 14
A14: W | B14: 0 | F14: Insight | G14: 0 | H14: I | I14: =IF(OR($I$12>0,G14=0),0,(G14^2+G14+2)) -> 0 | J14: =H14 -> I | K14: =OFFSET($B$1, MATCH(H14,$E$2:$E$9,0),0)+IF($G$12>0,$G$12+MIN(CEILING($B$13/2,1),$G$12),G14+IF(G14=0,-1,0)+MIN(CEILING($B$13/2,1),G14)) -> 8 | L14: Block | M14: - | N14: =M12+G24+MIN(CEILING(B13/2,1),G24)+O14+N34 -> 14
A15: U | B15: 19 | F15: Intimidation | G15: 0 | H15: C | I15: =IF(OR($I$12>0,G15=0),0,(G15^2+G15+2)) -> 0 | J15: =H15 -> C | K15: =OFFSET($B$1, MATCH(H15,$E$2:$E$9,0),0)+IF($G$12>0,$G$12+MIN(CEILING($B$13/2,1),$G$12),G15+IF(G15=0,-1,0)+MIN(CEILING($B$13/2,1),G15)) -> 1 | L15: Physical | M15: =B2+B3 -> 9 | N15: =M15+G27+MIN(CEILING(B13/2,1),G27)+O15 -> 19
A16: B | B16: 0 | F16: Negotiation | G16: 0 | H16: C | I16: =IF(OR($I$12>0,G16=0),0,(G16^2+G16+2)) -> 0 | J16: =H16 -> C | K16: =OFFSET($B$1, MATCH(H16,$E$2:$E$9,0),0)+IF($G$12>0,$G$12+MIN(CEILING($B$13/2,1),$G$12),G16+IF(G16=0,-1,0)+MIN(CEILING($B$13/2,1),G16)) -> 1 | L16: Mental | M16: =B6+B9 -> 10 | N16: =M16+G27+MIN(CEILING(B13/2,1),G27)+O16 -> 20
A17: R | B17: 11 | F17: SUBTERFUGE | G17: 0 | I17: =IF(G17>0,(G17^2+G17+2)*2.5,0) -> 0 | M17: 1 | N17: 2 | O17: 3
A18: G | B18: 0 | F18: Disguise | G18: 0 | H18: I | I18: =IF(OR($I$17>0,G18=0),0,(G18^2+G18+2)) -> 0 | J18: =H18 -> I | K18: =OFFSET($B$1, MATCH(H18,$E$2:$E$9,0),0)+IF($G$17>0,$G$17+MIN(CEILING($B$13/2,1),$G$17),G18+IF(G18=0,-1,0)+MIN(CEILING($B$13/2,1),G18)) -> 8 | M18: Melee | N18: Melee | O18: Melee
D19: Know discount | F19: Stealth | G19: 1 | H19: A | I19: =IF(OR($I$17>0,G19=0),0,(G19^2+G19+2)) -> 4 | J19: =H19 -> A | K19: =OFFSET($B$1, MATCH(H19,$E$2:$E$9,0),0)+IF($G$17>0,$G$17+MIN(CEILING($B$13/2,1),$G$17),G19+IF(G19=0,-1,0)+MIN(CEILING($B$13/2,1),G19)) -> 4 | L19: Name
A20: BP Current | B20: =SUM(D2:D10)+SUM(C13:C18)+SUM(I2:I44)+SUM(G37:G121)-MIN(SUM(I34:I44),D20) -> 2020 | D20: =(B8+B7)*10 -> 120 | F20: Legerdemain | G20: 3 | H20: A | I20: =IF(OR($I$17>0,G20=0),0,(G20^2+G20+2)) -> 14 | J20: =H20 -> A | K20: =OFFSET($B$1, MATCH(H20,$E$2:$E$9,0),0)+IF($G$17>0,$G$17+MIN(CEILING($B$13/2,1),$G$17),G20+IF(G20=0,-1,0)+MIN(CEILING($B$13/2,1),G20)) -> 8 | L20: Weapon | M20: Light | N20: 1H | O20: 2H
A21: BP Budget | B21: 2040 | F21: Thievery | G21: 0 | H21: A | I21: =IF(OR($I$17>0,G21=0),0,(G21^2+G21+2)) -> 0 | J21: =H21 -> A | K21: =OFFSET($B$1, MATCH(H21,$E$2:$E$9,0),0)+IF($G$17>0,$G$17+MIN(CEILING($B$13/2,1),$G$17),G21+IF(G21=0,-1,0)+MIN(CEILING($B$13/2,1),G21)) -> 1 | L21: Power | M21: 6 | N21: 8 | O21: 10 | Q21: Character Appearance Captain's hat, large and ink black with gold trim. A weather proof jacket in much the same style. An ash grey dress, flames seem to smolder as the dress flows, hints of deep reds and oranges. Her snake body, scaly from the waste down, with spines protruding. A snake-like torso with fish scales instead of skin, blue hued sandy colored on the front and darker on the back Centering Math Max Center: 28 Drain Soak (7 hits take 4) Max Overload: 11
F22: Spellcasting | G22: 9 | H22: =OFFSET($E$1, MATCH($B$11,$A$2:$A$10,0),0) -> I | I22: =IF(G22>0,(G22^2+G22+2),0) -> 92 | J22: =H22 -> I | K22: =OFFSET($B$1, MATCH(H22,$E$2:$E$9,0),0)+G22+MIN(CEILING($B$13/2,1),G22) -> 23 | L22: Reach | M22: =IF(M$18="Melee", OFFSET($B$24,0,MATCH(M$20,$C$23:$E$23,0))-M$21,0) -> -1 | N22: =IF(N$18="Melee", OFFSET($B$24,0,MATCH(N$20,$C$23:$E$23,0))-N$21,0) -> -2 | O22: =IF(O$18="Melee", OFFSET($B$24,0,MATCH(O$20,$C$23:$E$23,0))-O$21,0) -> -2
C23: Light | D23: 1H | E23: 2H | F23: Perceive Magic | G23: 5 | H23: =OFFSET($E$1, MATCH($B$11,$A$2:$A$10,0),0) -> I | I23: =IF(G23>0,(G23^2+G23+2),0) -> 32 | J23: =H23 -> I | K23: =OFFSET($B$1, MATCH(H23,$E$2:$E$9,0),0)+G23+MIN(CEILING($B$13/2,1),G23) -> 19 | L23: DV | M23: =M$21+$B$5 -> 8 | N23: =N$21+$B$5 -> 10 | O23: =O$21+$B$5 -> 12
C24: 5 | D24: 6 | E24: 8 | F24: (weapon skill) | G24: 0 | H24: A | I24: =IF(G24>0,(G24^2+G24+2),0) -> 0 | J24: =H24 -> A | K24: =OFFSET($B$1, MATCH(H24,$E$2:$E$9,0),0)+G24+MIN(CEILING($B$13/2,1),G24) -> 2 | L24: Dicepool | M24: =$K$24+M$22+IF(AND(M$20="2H",M$25="Buckler"),-2,0) -> 1 | N24: =$K$24+N$22+IF(AND(N$20="2H",N$25="Buckler"),-2,0) -> 0 | O24: =$K$24+O$22+IF(AND(O$20="2H",O$25="Buckler"),-2,0) -> 0
F25: Perception | G25: 5 | H25: I | I25: =IF(G25>0,(G25^2+G25+2),0) -> 32 | J25: =H25 -> I | K25: =OFFSET($B$1, MATCH(H25,$E$2:$E$9,0),0)+G25+MIN(CEILING($B$13/2,1),G25) -> 19 | L25: Shield | M25: None | N25: None | O25: None
F26: Dodge | G26: 7 | H26: N/A | I26: =IF(G26>0,(G26^2+G26+2),0) -> 58 | L26: Shield Bonus | M26: =OFFSET($D$30,MATCH(M$25,$D$26:$D$31,0),0) -> 0 | N26: =OFFSET($D$30,MATCH(N$25,$D$26:$D$31,0),0) -> 0 | O26: =OFFSET($D$30,MATCH(O$25,$D$26:$D$31,0),0) -> 0
C27: None | D27: None | E27: None | F27: Perserverence | G27: 5 | H27: N/A | I27: =IF(G27>0,(G27^2+G27+2),0) -> 32 | M27: Weapon # | N27: 1
B28: Magical Theory | C28: Buckler | D28: Buckler | E28: Buckler | F28: Knowledge | G28: 0 | H28: =J28 -> L | I28: =IF(G28>0,(G28^2+G28+2),0)/2 -> 0 | J28: L | K28: =OFFSET($B$1, MATCH(H28,$E$2:$E$9,0),0)+G28+MIN(CEILING($B$13/2,1),G28) -> 3 | M28: Weapon | N28: =OFFSET(L20,0,$N$27) -> Light | O28: X foot reach
B29: Writing | C29: Medium | D29: Medium | F29: Knowledge | G29: 0 | H29: =J29 -> L | I29: =IF(G29>0,(G29^2+G29+2),0)/2 -> 0 | J29: L | K29: =OFFSET($B$1, MATCH(H29,$E$2:$E$9,0),0)+G29+MIN(CEILING($B$13/2,1),G29) -> 3 | M29: Power | N29: =OFFSET(L21,0,$N$27)-2*(O33<>"None") -> 6 | O29: =MAX(0,FLOOR(N30/2,1)-1)*5+5 -> 5
B30: Art | C30: Heavy | D30: Heavy | F30: Knowledge | G30: 0 | H30: =J30 -> L | I30: =IF(G30>0,(G30^2+G30+2),0)/2 -> 0 | J30: L | K30: =OFFSET($B$1, MATCH(H30,$E$2:$E$9,0),0)+G30+MIN(CEILING($B$13/2,1),G30) -> 3 | M30: Reach | N30: =OFFSET(L22,0,$N$27)+O31 -> 0 | O30: Reach Bonus
B31: Astronomy | C31: Tower | D31: Tower | F31: Knowledge | G31: 0 | H31: =J31 -> L | I31: =IF(G31>0,(G31^2+G31+2),0)/2 -> 0 | J31: L | K31: =OFFSET($B$1, MATCH(H31,$E$2:$E$9,0),0)+G31+MIN(CEILING($B$13/2,1),G31) -> 3 | M31: DV | N31: =OFFSET(L23,0,$N$27) -> 8 | O31: 1 | Q31: Vial from Genie room 3 alchemical phoenix fire vials 5 reams of mica tablets Coat of always clean Lich's Sceptre (powering Iobia's planetarium) Ring of Illumination (small amount of light) Shadowy Quill (shadowless cursed) Cloak of Ele Res (resists last hit element, res 3) 6 bottles of phoenix blood 2 feathers Water Cube => absorbs water, keeps objects it touches moist, can launch water (water shield, water bubble) Backpack of Holding full of someone's bag of holding of loot
C32: =OFFSET(B27,0,MATCH($M$20,$C$23:$E$23,0)) -> None | D32: 0 | F32: Knowledge | G32: 0 | H32: =J32 -> I | I32: =IF(G32>0,(G32^2+G32+2),0)/2 -> 0 | J32: I | K32: =OFFSET($B$1, MATCH(H32,$E$2:$E$9,0),0)+G32+MIN(CEILING($B$13/2,1),G32) -> 9 | M32: Dicepool | N32: =OFFSET(L24,0,$N$27) -> 1 | O32: ELEMENT
C33: =OFFSET(B28,0,MATCH($M$20,$C$23:$E$23,0)) -> Buckler | D33: 1 | F33: Knowledge | G33: 0 | H33: =J33 -> I | I33: =IF(G33>0,(G33^2+G33+2),0)/2 -> 0 | J33: I | K33: =OFFSET($B$1, MATCH(H33,$E$2:$E$9,0),0)+G33+MIN(CEILING($B$13/2,1),G33) -> 9 | M33: Shield | N33: =OFFSET(L25,0,$N$27) -> None | O33: None
C34: =OFFSET(B29,0,MATCH($M$20,$C$23:$E$23,0)) -> Medium | D34: 4 | F34: Knowledge | G34: 0 | H34: =J34 -> I | I34: =IF(G34>0,(G34^2+G34+2),0)/2 -> 0 | J34: I | K34: =OFFSET($B$1, MATCH(H34,$E$2:$E$9,0),0)+G34+MIN(CEILING($B$13/2,1),G34) -> 9 | M34: Shield Bonus | N34: =OFFSET(L26,0,$N$27) -> 0
C35: =OFFSET(B30,0,MATCH($M$20,$C$23:$E$23,0)) -> Heavy | D35: 5 | F35: Knowledge | G35: 0 | H35: =J35 -> I | I35: =IF(G35>0,(G35^2+G35+2),0)/2 -> 0 | J35: I | K35: =OFFSET($B$1, MATCH(H35,$E$2:$E$9,0),0)+G35+MIN(CEILING($B$13/2,1),G35) -> 9
C36: =OFFSET(B31,0,MATCH($M$20,$C$23:$E$23,0)) -> Tower | D36: 7 | F36: Knowledge | G36: 0 | H36: =J36 -> I | I36: =IF(G36>0,(G36^2+G36+2),0)/2 -> 0 | J36: I | K36: =OFFSET($B$1, MATCH(H36,$E$2:$E$9,0),0)+G36+MIN(CEILING($B$13/2,1),G36) -> 9
B39: Abilities
A40: Rank | B40: Name | G40: Cost | J40: Affinity
A41: 1 | B41: Photographic memory | G41: =IFERROR(OFFSET(Abilities!$N$1,MATCH(B41,Abilities!C:C,0)-1,A41),0) -> 3 | J41: =OFFSET(Abilities!$N$1,MATCH(B41,Abilities!C:C,0)-1,-7) -> 3U,(6) | K41: =OFFSET(Abilities!$N$1,MATCH(B41,Abilities!C:C,0)-1,-12) -> Passive | L41: =OFFSET(Abilities!$N$1,MATCH(B41,Abilities!C:C,0)-1,-9) -> Gain 2 dice on knowledge checks to remember something. You may recall additional relevant details by prompting the GM for a clearer picture of a memory, subject to GM discretion. Rolling memory is now faster (typically a Extra action).
A42: 1 | B42: Mcguiver | G42: =IFERROR(OFFSET(Abilities!$N$1,MATCH(B42,Abilities!C:C,0)-1,A42),0) -> 5 | J42: =OFFSET(Abilities!$N$1,MATCH(B42,Abilities!C:C,0)-1,-7) -> 7(U|R),(9) | K42: =OFFSET(Abilities!$N$1,MATCH(B42,Abilities!C:C,0)-1,-12) -> Manuever | L42: =OFFSET(Abilities!$N$1,MATCH(B42,Abilities!C:C,0)-1,-9) -> You may attempt to fix or break mechanical and/or magical devices such as locks or crystal balls. Who knows what will happen! (needs actual rules ffs)
A43: 1 | B43: Supreme Contortionist | G43: =IFERROR(OFFSET(Abilities!$N$1,MATCH(B43,Abilities!C:C,0)-1,A43),0) -> 3 | J43: =OFFSET(Abilities!$N$1,MATCH(B43,Abilities!C:C,0)-1,-7) -> 1R,(3) | K43: =OFFSET(Abilities!$N$1,MATCH(B43,Abilities!C:C,0)-1,-12) -> Passive | L43: =OFFSET(Abilities!$N$1,MATCH(B43,Abilities!C:C,0)-1,-9) -> You can contort and deform your body to fit in/through spaces smaller than normal.
A44: 1 | B44: Water Walking | G44: =IFERROR(OFFSET(Abilities!$N$1,MATCH(B44,Abilities!C:C,0)-1,A44),0) -> 5 | J44: =OFFSET(Abilities!$N$1,MATCH(B44,Abilities!C:C,0)-1,-7) -> 7(U|G),(9) | K44: =OFFSET(Abilities!$N$1,MATCH(B44,Abilities!C:C,0)-1,-12) -> Passive | L44: =OFFSET(Abilities!$N$1,MATCH(B44,Abilities!C:C,0)-1,-9) -> You can walk on water as if it were solid ground
A45: 1 | B45: Spring up | G45: =IFERROR(OFFSET(Abilities!$N$1,MATCH(B45,Abilities!C:C,0)-1,A45),0) -> 4 | J45: =OFFSET(Abilities!$N$1,MATCH(B45,Abilities!C:C,0)-1,-7) -> 2(R|G),(3) | K45: =OFFSET(Abilities!$N$1,MATCH(B45,Abilities!C:C,0)-1,-12) -> Maneuver | L45: =OFFSET(Abilities!$N$1,MATCH(B45,Abilities!C:C,0)-1,-9) -> Stand up as Extra action that does not provoke attacks of opportunity. All your jumps are treated as having a running start.
A46: 1 | B46: Spiderclimb | G46: =IFERROR(OFFSET(Abilities!$N$1,MATCH(B46,Abilities!C:C,0)-1,A46),0) -> 10 | J46: =OFFSET(Abilities!$N$1,MATCH(B46,Abilities!C:C,0)-1,-7) -> 9(G|R),(12) | K46: =OFFSET(Abilities!$N$1,MATCH(B46,Abilities!C:C,0)-1,-12) -> Passive | L46: =OFFSET(Abilities!$N$1,MATCH(B46,Abilities!C:C,0)-1,-9) -> You can walk on walls as easily as ground. Climb checks are still required, thresholds are lowered.
A47: 1 | B47: Chaotic Haversack | G47: =IFERROR(OFFSET(Abilities!$N$1,MATCH(B47,Abilities!C:C,0)-1,A47),0) -> 5 | J47: =OFFSET(Abilities!$N$1,MATCH(B47,Abilities!C:C,0)-1,-7) -> 4R,3(U|R|G),(9) | K47: =OFFSET(Abilities!$N$1,MATCH(B47,Abilities!C:C,0)-1,-12) -> Passive | L47: =OFFSET(Abilities!$N$1,MATCH(B47,Abilities!C:C,0)-1,-9) -> As a standard action, you may pull out any half non-magical inanimate object (rope, candle, etc). You may have up to a total of 3 spontaneously generated items at a time; these items may be returned to the sack and exchanged. Items spontaneously created are entirely mundane items posessing no magical properties. Should a spontaneously generated item be unreturned to the sack there is a 24 hour period before that use is restored. Ability to pull out various low value items without specifically having them in inventory, representing character's collection of useful odds and ends. Pull out an item based on hits: 1. basic object 2. half item 4. full item 5. exotic substance Dicepool of LOG+INT+3
A48: 1 | B48: It's all in the wrist | G48: =IFERROR(OFFSET(Abilities!$N$1,MATCH(B48,Abilities!C:C,0)-1,A48),0) -> 5 | J48: =OFFSET(Abilities!$N$1,MATCH(B48,Abilities!C:C,0)-1,-7) -> 4(U|R),(6) | K48: =OFFSET(Abilities!$N$1,MATCH(B48,Abilities!C:C,0)-1,-12) -> Passive | L48: =OFFSET(Abilities!$N$1,MATCH(B48,Abilities!C:C,0)-1,-9) -> You may make a legerdemain check to make games of chance end in your favor. Gain +4 dice to these checks, you may spend a luck point to ensure a victory. Additionally, you may spend a point of luck to win a bet limited to gambling such as betting on a fight or race. May apply circumstance bonuses at the GMs discretion.
A49: 3 | B49: Blink | G49: =IFERROR(OFFSET(Abilities!$N$1,MATCH(B49,Abilities!C:C,0)-1,A49),0) -> 135 | J49: =OFFSET(Abilities!$N$1,MATCH(B49,Abilities!C:C,0)-1,-7) -> 7U,(15) 10U,(21) 13U,(27) | K49: =OFFSET(Abilities!$N$1,MATCH(B49,Abilities!C:C,0)-1,-12) -> Maneuver | L49: =OFFSET(Abilities!$N$1,MATCH(B49,Abilities!C:C,0)-1,-9) -> Extra action, teleport up to your 30ft to a square within line of sight. The next use of this ability costs 10/1/0 more stamina. The stamina cost of this ability decreases by 1 at the end of the round.
A50: 1 | B50: Spatial Slip | G50: =IFERROR(OFFSET(Abilities!$N$1,MATCH(B50,Abilities!C:C,0)-1,A50),0) -> 5 | J50: =OFFSET(Abilities!$N$1,MATCH(B50,Abilities!C:C,0)-1,-7) -> 9U,(18) | K50: =OFFSET(Abilities!$N$1,MATCH(B50,Abilities!C:C,0)-1,-12) -> Maneuver | L50: =OFFSET(Abilities!$N$1,MATCH(B50,Abilities!C:C,0)-1,-9) -> spend an additional (5) as part of a dodge. Gain +5 dice, after resolving the dodge you may trigger one of your Extra action teleportation abilities as a nonaction.
A51: 1 | B51: Phasing | G51: =IFERROR(OFFSET(Abilities!$N$1,MATCH(B51,Abilities!C:C,0)-1,A51),0) -> 20 | J51: =OFFSET(Abilities!$N$1,MATCH(B51,Abilities!C:C,0)-1,-7) -> 6U,(12) 9U,(18) 12U,(24) 15U,(30) | K51: =OFFSET(Abilities!$N$1,MATCH(B51,Abilities!C:C,0)-1,-12) -> Maneuver | L51: =OFFSET(Abilities!$N$1,MATCH(B51,Abilities!C:C,0)-1,-9) -> As a half action you may fully pass through thin materials and structures up to a few inches thick. Lead and other specific materials cannot be so bypassed. This increases the cost of subsequent phasings by 10 stamina, this cost decays by 1 at the end of each round down to a minimum of 0. _____________________________________ As previous rank, except you may pass through up to a foot in thickness. Cost increase is 8 instead of 10 _____________________________________ As previous rank, except you may pass through up to 10'. Cost increase is 6 instead of 8 _____________________________________ As previous rank, except the cost increase is 4 instead of 6. With all ranks, if you fail to fully traverse when phasing you are shunted back out to where you started, taking 2 lethal per foot of distance so displaced (rounded up).
A52: 1 | B52: Counterspell | G52: =IFERROR(OFFSET(Abilities!$N$1,MATCH(B52,Abilities!C:C,0)-1,A52),0) -> 5 | J52: =OFFSET(Abilities!$N$1,MATCH(B52,Abilities!C:C,0)-1,-7) -> 7U,(9) | K52: =OFFSET(Abilities!$N$1,MATCH(B52,Abilities!C:C,0)-1,-12) -> Maneuver | L52: =OFFSET(Abilities!$N$1,MATCH(B52,Abilities!C:C,0)-1,-9) -> (10) as interrupt, attempt to counter a spell. Roll Cast stat + spellcasting skill + other bonuses vs. the spellcaster's roll in place of a normal resistance check.
... A54: 1 | B54: Burnout | G54: =IFERROR(OFFSET(Abilities!$N$1,MATCH(B54,Abilities!C:C,0)-1,A54),0) -> 20 | J54: =OFFSET(Abilities!$N$1,MATCH(B54,Abilities!C:C,0)-1,-7) -> 7R,(9) | K54: =OFFSET(Abilities!$N$1,MATCH(B54,Abilities!C:C,0)-1,-12) -> Maneuver | L54: =OFFSET(Abilities!$N$1,MATCH(B54,Abilities!C:C,0)-1,-9) -> Roll an init die twice, lose acces to that init die for the following round
A55: 1 | G55: =IFERROR(OFFSET(Abilities!$N$1,MATCH(B55,Abilities!C:C,0)-1,A55),0) -> 0 | J55: =OFFSET(Abilities!$N$1,MATCH(B55,Abilities!C:C,0)-1,-7) -> #N/A | K55: =OFFSET(Abilities!$N$1,MATCH(B55,Abilities!C:C,0)-1,-12) -> #N/A | L55: =OFFSET(Abilities!$N$1,MATCH(B55,Abilities!C:C,0)-1,-9) -> #N/A
A56: 1 | B56: Prescient Teleport | G56: =IFERROR(OFFSET(Abilities!$N$1,MATCH(B56,Abilities!C:C,0)-1,A56),0) -> 40 | J56: =OFFSET(Abilities!$N$1,MATCH(B56,Abilities!C:C,0)-1,-7) -> 19U,(24) | K56: =OFFSET(Abilities!$N$1,MATCH(B56,Abilities!C:C,0)-1,-12) -> Maneuver | L56: =OFFSET(Abilities!$N$1,MATCH(B56,Abilities!C:C,0)-1,-9) -> (5) as a nonaction at any time. Resolve one of your teleportation abilities.
A57: 1 | G57: =IFERROR(OFFSET(Abilities!$N$1,MATCH(B57,Abilities!C:C,0)-1,A57),0) -> 0 | J57: =OFFSET(Abilities!$N$1,MATCH(B57,Abilities!C:C,0)-1,-7) -> #N/A | K57: =OFFSET(Abilities!$N$1,MATCH(B57,Abilities!C:C,0)-1,-12) -> #N/A | L57: =OFFSET(Abilities!$N$1,MATCH(B57,Abilities!C:C,0)-1,-9) -> #N/A
A58: 1 | G58: =IFERROR(OFFSET(Abilities!$N$1,MATCH(B58,Abilities!C:C,0)-1,A58),0) -> 0 | J58: =OFFSET(Abilities!$N$1,MATCH(B58,Abilities!C:C,0)-1,-7) -> #N/A | K58: =OFFSET(Abilities!$N$1,MATCH(B58,Abilities!C:C,0)-1,-12) -> #N/A | L58: =OFFSET(Abilities!$N$1,MATCH(B58,Abilities!C:C,0)-1,-9) -> #N/A
A59: 1 | B59: dodge stance | G59: =IFERROR(OFFSET(Abilities!$N$1,MATCH(B59,Abilities!C:C,0)-1,A59),0) -> 10 | J59: =OFFSET(Abilities!$N$1,MATCH(B59,Abilities!C:C,0)-1,-7) -> 9(U|B|R),(12) | K59: =OFFSET(Abilities!$N$1,MATCH(B59,Abilities!C:C,0)-1,-12) -> Stance | L59: =OFFSET(Abilities!$N$1,MATCH(B59,Abilities!C:C,0)-1,-9) -> Every time you attempt a dodge you may shift 5ft after resolving the dodge.
A60: 1 | G60: =IFERROR(OFFSET(Abilities!$N$1,MATCH(B60,Abilities!C:C,0)-1,A60),0) -> 0 | J60: =OFFSET(Abilities!$N$1,MATCH(B60,Abilities!C:C,0)-1,-7) -> #N/A | K60: =OFFSET(Abilities!$N$1,MATCH(B60,Abilities!C:C,0)-1,-12) -> #N/A | L60: =OFFSET(Abilities!$N$1,MATCH(B60,Abilities!C:C,0)-1,-9) -> #N/A
A61: 1 | B61: Clairvoyance | G61: =IFERROR(OFFSET(Abilities!$N$1,MATCH(B61,Abilities!C:C,0)-1,A61),0) -> 5 | J61: =OFFSET(Abilities!$N$1,MATCH(B61,Abilities!C:C,0)-1,-7) -> 4U,(9) | K61: =OFFSET(Abilities!$N$1,MATCH(B61,Abilities!C:C,0)-1,-12) -> Spell | L61: =OFFSET(Abilities!$N$1,MATCH(B61,Abilities!C:C,0)-1,-9) -> SUST SELF Range = CS*10ft You create a scrying sensor at a nearby location within RANGE. You can see and hear as if you are at that location. Casting this spell is a half action. Overloads 2: +CS*10 ft range
A62: 1 | B62: Fling | G62: =IFERROR(OFFSET(Abilities!$N$1,MATCH(B62,Abilities!C:C,0)-1,A62),0) -> 5 | J62: =OFFSET(Abilities!$N$1,MATCH(B62,Abilities!C:C,0)-1,-7) -> 3R,(6) | K62: =OFFSET(Abilities!$N$1,MATCH(B62,Abilities!C:C,0)-1,-12) -> Spell | L62: =OFFSET(Abilities!$N$1,MATCH(B62,Abilities!C:C,0)-1,-9) -> INST TRGT Throw an object with effective STR = CS-2 When throwing a weapon or other similarly sized item (limited to weapons of your size) you may resolve the fling as an attack roll when directing the object at a specific target. When throwing larger objects the item is treated as a falling object and creatures in the target zone are entitled to a dodge(2) threshold check to avoid it. Overloads 2: +1 effective STR
A63: 1 | B63: Fog | G63: =IFERROR(OFFSET(Abilities!$N$1,MATCH(B63,Abilities!C:C,0)-1,A63),0) -> 5 | J63: =OFFSET(Abilities!$N$1,MATCH(B63,Abilities!C:C,0)-1,-7) -> 4(U|G),(9) | K63: =OFFSET(Abilities!$N$1,MATCH(B63,Abilities!C:C,0)-1,-12) -> Spell | L63: =OFFSET(Abilities!$N$1,MATCH(B63,Abilities!C:C,0)-1,-9) -> SUST 5ft diameter per CS first 5ft of fog grant moderate concealment, 10ft+ total concealment. Overloads 3: +5ft diameter
A64: 1 | B64: Levitate | G64: =IFERROR(OFFSET(Abilities!$N$1,MATCH(B64,Abilities!C:C,0)-1,A64),0) -> 5 | J64: =OFFSET(Abilities!$N$1,MATCH(B64,Abilities!C:C,0)-1,-7) -> 3U,(6) | K64: =OFFSET(Abilities!$N$1,MATCH(B64,Abilities!C:C,0)-1,-12) -> Spell | L64: =OFFSET(Abilities!$N$1,MATCH(B64,Abilities!C:C,0)-1,-9) -> SUST TRGT Range = 30 ft Lift up to 50kg per CS (single object or clump of objects) Or up to SPELLCASTING individual objects of negligible weight Can only target attended objects if the attendee is willing Cannot move objects that are stuck or restrained Affecting a creature requires an opposed check eDV = CS-1 mental/phys 0: no effect 1+: the target is lifted up and dropped prone if they fail a (2) acrobatics check 9+ the target is levitated until the end of the round Overloads 2: +1 eDV 2: +5ft range You can move the target at a rate of 5ft per half action, or in the case of multiple small objects, 20ft. As a half action you can also set the object(s) to follow you, but they are limited to traveling at the listed speeds per round and move at the end of the round. Targets can be raised at most 30ft off the ground and if moved to be higher will descend safely at 60ft per round.
A65: 1 | B65: Sending | G65: =IFERROR(OFFSET(Abilities!$N$1,MATCH(B65,Abilities!C:C,0)-1,A65),0) -> 5 | J65: =OFFSET(Abilities!$N$1,MATCH(B65,Abilities!C:C,0)-1,-7) -> 4U,(9) | K65: =OFFSET(Abilities!$N$1,MATCH(B65,Abilities!C:C,0)-1,-12) -> Spell | L65: =OFFSET(Abilities!$N$1,MATCH(B65,Abilities!C:C,0)-1,-9) -> INST Send a message of 25 words up to (CS*10) feet to a known recipient. Overloads: 3: *10 distance 3: send a picture instead
A66: 1 | B66: Shatter | G66: =IFERROR(OFFSET(Abilities!$N$1,MATCH(B66,Abilities!C:C,0)-1,A66),0) -> 10 | J66: =OFFSET(Abilities!$N$1,MATCH(B66,Abilities!C:C,0)-1,-7) -> 7(W|R|G),(9) | K66: =OFFSET(Abilities!$N$1,MATCH(B66,Abilities!C:C,0)-1,-12) -> Spell | L66: =OFFSET(Abilities!$N$1,MATCH(B66,Abilities!C:C,0)-1,-9) -> DIRECT INST DV = CS+3 Can only target objects. Attended objects are entitled to physical resist and physical soak on top of their hardness. Overloads: 2: +1 eDV
A67: 1 | B67: Elemental Blast | G67: =IFERROR(OFFSET(Abilities!$N$1,MATCH(B67,Abilities!C:C,0)-1,A67),0) -> 5 | J67: =OFFSET(Abilities!$N$1,MATCH(B67,Abilities!C:C,0)-1,-7) -> 4*C*,(9) | K67: =OFFSET(Abilities!$N$1,MATCH(B67,Abilities!C:C,0)-1,-12) -> Spell | L67: =OFFSET(Abilities!$N$1,MATCH(B67,Abilities!C:C,0)-1,-9) -> INST/SUST Touch (non provoking), ranged DV = CS+1 (ELEMENT) Resist = Dodge,Block Soak = Armor Overloads 2: +1DV 2: AoE per 5ft diameter, (note that it starts at 5ft effectively) 4: Sust (repeat the attack at the target location at the end of every round it is sustained. This repeat attack is always treated as an AoE. You may move the target area of this sustained spell as a half action.) This attack does elemental damage of the chosen type, fixed upon purchase of ability.
A68: 1 | B68: Vault | G68: =IFERROR(OFFSET(Abilities!$N$1,MATCH(B68,Abilities!C:C,0)-1,A68),0) -> 5 | J68: =OFFSET(Abilities!$N$1,MATCH(B68,Abilities!C:C,0)-1,-7) -> 8(U|R|B|W),(9) | K68: =OFFSET(Abilities!$N$1,MATCH(B68,Abilities!C:C,0)-1,-12) -> Maneuver | L68: =OFFSET(Abilities!$N$1,MATCH(B68,Abilities!C:C,0)-1,-9) -> half Action. One ally within (60 ft) gains a fly speed equal to their movement speed until the end of the round.
A69: 1 | B69: Ice Conjuring | G69: =IFERROR(OFFSET(Abilities!$N$1,MATCH(B69,Abilities!C:C,0)-1,A69),0) -> 25 | J69: =OFFSET(Abilities!$N$1,MATCH(B69,Abilities!C:C,0)-1,-7) -> 7U,(15) | K69: =OFFSET(Abilities!$N$1,MATCH(B69,Abilities!C:C,0)-1,-12) -> Spell | L69: =OFFSET(Abilities!$N$1,MATCH(B69,Abilities!C:C,0)-1,-9) -> INST You can conjure ice into any shape that suits your purpose. While it’s possible to make crude coffers, doors, and so forth with this function, fine detail isn’t possible. (10 cubic feet per CS/2). For surfaces you can choose rough (nonslip) or smooth (checks required) ice. Ice has (3 HP per cubic foot and barrier rating 5) . (40 cubic feet per CS/2) of existing ice may be reshaped instead. Ice cannot be conjured into occupied space, cannot exert force in the conjuring process, or be conjured flush with intricate surfaces. Overloads: (2): +10 cubic feet conjured (2): +40 cubic feet reshaped You can form ice with focused detail into an object that suits your purpose. You may create multiple items as part of the same action up to a total of CS/6 items. If shaping the item from existing ice, you may instead create one item per CS/2. Overloads: (6): +1 item with no preexisting ice (2): +1 item with preexisting ice You can flash freeze existing water and liquids that are not part of living or animate creatures, you may be able to use this as an attack against specific creatures with your GM's discretion (A creature formed entirely of water). If the objects are attended they are entitled to resist. (If targeting attended liquids) eDV = CS+4 Mental resist/Physical soak Freeze 5 cubic feet per unsoaked eDV Overloads: (2): +1 eDV
A70: 1 | B70: Ability Name | G70: =IFERROR(OFFSET(Abilities!$N$1,MATCH(B70,Abilities!C:C,0)-1,A70),0) -> R1 | J70: =OFFSET(Abilities!$N$1,MATCH(B70,Abilities!C:C,0)-1,-7) -> Affinity req | K70: =OFFSET(Abilities!$N$1,MATCH(B70,Abilities!C:C,0)-1,-12) -> Category | L70: =OFFSET(Abilities!$N$1,MATCH(B70,Abilities!C:C,0)-1,-9) -> Rules Text
A71: 1 | B71: Centering Technique | G71: =IFERROR(OFFSET(Abilities!$N$1,MATCH(B71,Abilities!C:C,0)-1,A71),0) -> 0 | J71: =OFFSET(Abilities!$N$1,MATCH(B71,Abilities!C:C,0)-1,-7) -> WUBRG,(0) | K71: =OFFSET(Abilities!$N$1,MATCH(B71,Abilities!C:C,0)-1,-12) -> Metamagic | L71: =OFFSET(Abilities!$N$1,MATCH(B71,Abilities!C:C,0)-1,-9) -> Complex Action. Begin centering to cast a spell on a later turn. Each consecutive turn that you center adds the following: WIL/2 to the drain dicepool up to a cap of 2*WIL, overload limit of the spell by 1 up to a total cap of CAST STAT+4. If you are subjected to an effect that would prevent you from using this ability then your current centering is lost. Possessing this ability incurs a 2 drain cost on any spells cast without centering (Note this is an up front cost, not an overload value).
A72: 1 | B72: Unstable Artifice | G72: =IFERROR(OFFSET(Abilities!$N$1,MATCH(B72,Abilities!C:C,0)-1,A72),0) -> 100 | J72: =OFFSET(Abilities!$N$1,MATCH(B72,Abilities!C:C,0)-1,-7) -> 8U,8R,8(U|R),(30) | K72: =OFFSET(Abilities!$N$1,MATCH(B72,Abilities!C:C,0)-1,-12) -> Metamagic | L72: =OFFSET(Abilities!$N$1,MATCH(B72,Abilities!C:C,0)-1,-9) -> Whenever you take X drain from spellcasting roll a dicepool of X size. For every hit that results copy the triggering spell. These copies do not incur drain.
... A74: 1 | B74: Fork | G74: =IFERROR(OFFSET(Abilities!$N$1,MATCH(B74,Abilities!C:C,0)-1,A74),0) -> 10 | J74: =OFFSET(Abilities!$N$1,MATCH(B74,Abilities!C:C,0)-1,-7) -> 7R,(9) | K74: =OFFSET(Abilities!$N$1,MATCH(B74,Abilities!C:C,0)-1,-12) -> Metamagic | L74: =OFFSET(Abilities!$N$1,MATCH(B74,Abilities!C:C,0)-1,-9) -> Overload 6, copy this spell. The copied spell does not inherit Fork.
A75: 1 | G75: =IFERROR(OFFSET(Abilities!$N$1,MATCH(B75,Abilities!C:C,0)-1,A75),0) -> 0 | J75: =OFFSET(Abilities!$N$1,MATCH(B75,Abilities!C:C,0)-1,-7) -> #N/A | K75: =OFFSET(Abilities!$N$1,MATCH(B75,Abilities!C:C,0)-1,-12) -> #N/A | L75: =OFFSET(Abilities!$N$1,MATCH(B75,Abilities!C:C,0)-1,-9) -> #N/A
A76: 3 | B76: Lightning Reflexes | G76: =IFERROR(OFFSET(Abilities!$N$1,MATCH(B76,Abilities!C:C,0)-1,A76),0) -> 120 | J76: =OFFSET(Abilities!$N$1,MATCH(B76,Abilities!C:C,0)-1,-7) -> ,(12) (18) (24) | K76: =OFFSET(Abilities!$N$1,MATCH(B76,Abilities!C:C,0)-1,-12) -> Passive | L76: =OFFSET(Abilities!$N$1,MATCH(B76,Abilities!C:C,0)-1,-9) -> (RANK) extra initiative dice
A77: 1 | B77: Lightning Rod | G77: =IFERROR(OFFSET(Abilities!$N$1,MATCH(B77,Abilities!C:C,0)-1,A77),0) -> 15 | J77: =OFFSET(Abilities!$N$1,MATCH(B77,Abilities!C:C,0)-1,-7) -> 4U,4R,(18) | K77: =OFFSET(Abilities!$N$1,MATCH(B77,Abilities!C:C,0)-1,-12) -> Passive | L77: =OFFSET(Abilities!$N$1,MATCH(B77,Abilities!C:C,0)-1,-9) -> Your lightning damage cannot normally apply thunderstruck. Enemies damaged by your lightning effects suffer Vulnerable 2 to lightning until the end of next round. Damaging an enemy with a lightning effect grants you one static charge. Static charges decay after 1 minute of not gaining a charge. While holding at least one static charge you glow faintly. You can spend static charges as follows. (X): This lightning attack can apply thunderstruck, count your net hits as X higher for determining if thunderstruck occurs. This may be activated after net hits are determined. (3): Select one creature up to 30ft away from a current target for your lightning attack as an additional target, there must be line of effect between these two creatures.
A78: 1 | G78: =IFERROR(OFFSET(Abilities!$N$1,MATCH(B78,Abilities!C:C,0)-1,A78),0) -> 0 | J78: =OFFSET(Abilities!$N$1,MATCH(B78,Abilities!C:C,0)-1,-7) -> #N/A | K78: =OFFSET(Abilities!$N$1,MATCH(B78,Abilities!C:C,0)-1,-12) -> #N/A | L78: =OFFSET(Abilities!$N$1,MATCH(B78,Abilities!C:C,0)-1,-9) -> #N/A
A79: 1 | G79: =IFERROR(OFFSET(Abilities!$N$1,MATCH(B79,Abilities!C:C,0)-1,A79),0) -> 0 | J79: =OFFSET(Abilities!$N$1,MATCH(B79,Abilities!C:C,0)-1,-7) -> #N/A | K79: =OFFSET(Abilities!$N$1,MATCH(B79,Abilities!C:C,0)-1,-12) -> #N/A | L79: =OFFSET(Abilities!$N$1,MATCH(B79,Abilities!C:C,0)-1,-9) -> #N/A
A80: 1 | G80: =IFERROR(OFFSET(Abilities!$N$1,MATCH(B80,Abilities!C:C,0)-1,A80),0) -> 0 | J80: =OFFSET(Abilities!$N$1,MATCH(B80,Abilities!C:C,0)-1,-7) -> #N/A | K80: =OFFSET(Abilities!$N$1,MATCH(B80,Abilities!C:C,0)-1,-12) -> #N/A | L80: =OFFSET(Abilities!$N$1,MATCH(B80,Abilities!C:C,0)-1,-9) -> #N/A
A81: 1 | G81: =IFERROR(OFFSET(Abilities!$N$1,MATCH(B81,Abilities!C:C,0)-1,A81),0) -> 0 | J81: =OFFSET(Abilities!$N$1,MATCH(B81,Abilities!C:C,0)-1,-7) -> #N/A | K81: =OFFSET(Abilities!$N$1,MATCH(B81,Abilities!C:C,0)-1,-12) -> #N/A | L81: =OFFSET(Abilities!$N$1,MATCH(B81,Abilities!C:C,0)-1,-9) -> #N/A
A82: 1 | G82: =IFERROR(OFFSET(Abilities!$N$1,MATCH(B82,Abilities!C:C,0)-1,A82),0) -> 0 | J82: =OFFSET(Abilities!$N$1,MATCH(B82,Abilities!C:C,0)-1,-7) -> #N/A | K82: =OFFSET(Abilities!$N$1,MATCH(B82,Abilities!C:C,0)-1,-12) -> #N/A | L82: =OFFSET(Abilities!$N$1,MATCH(B82,Abilities!C:C,0)-1,-9) -> #N/A
A83: 2 | G83: =IFERROR(OFFSET(Abilities!$N$1,MATCH(B83,Abilities!C:C,0)-1,A83),0) -> 0 | J83: =OFFSET(Abilities!$N$1,MATCH(B83,Abilities!C:C,0)-1,-7) -> #N/A | K83: =OFFSET(Abilities!$N$1,MATCH(B83,Abilities!C:C,0)-1,-12) -> #N/A | L83: =OFFSET(Abilities!$N$1,MATCH(B83,Abilities!C:C,0)-1,-9) -> #N/A
A84: 1 | G84: =IFERROR(OFFSET(Abilities!$N$1,MATCH(B84,Abilities!C:C,0)-1,A84),0) -> 0 | J84: =OFFSET(Abilities!$N$1,MATCH(B84,Abilities!C:C,0)-1,-7) -> #N/A | K84: =OFFSET(Abilities!$N$1,MATCH(B84,Abilities!C:C,0)-1,-12) -> #N/A | L84: =OFFSET(Abilities!$N$1,MATCH(B84,Abilities!C:C,0)-1,-9) -> #N/A
A85: 1 | B85: Darkvision | G85: =IFERROR(OFFSET(Abilities!$N$1,MATCH(B85,Abilities!C:C,0)-1,A85),0) -> 5 | J85: =OFFSET(Abilities!$N$1,MATCH(B85,Abilities!C:C,0)-1,-7) -> 3(B|G|R),(9) per | K85: =OFFSET(Abilities!$N$1,MATCH(B85,Abilities!C:C,0)-1,-12) -> Passive | L85: =OFFSET(Abilities!$N$1,MATCH(B85,Abilities!C:C,0)-1,-9) -> 30/60/120ft darkvision
A86: 1 | G86: =IFERROR(OFFSET(Abilities!$N$1,MATCH(B86,Abilities!C:C,0)-1,A86),0) -> 0 | J86: =OFFSET(Abilities!$N$1,MATCH(B86,Abilities!C:C,0)-1,-7) -> #N/A | K86: =OFFSET(Abilities!$N$1,MATCH(B86,Abilities!C:C,0)-1,-12) -> #N/A | L86: =OFFSET(Abilities!$N$1,MATCH(B86,Abilities!C:C,0)-1,-9) -> #N/A
A87: 1 | B87: Ability Name | G87: =IFERROR(OFFSET(Abilities!$N$1,MATCH(B87,Abilities!C:C,0)-1,A87),0) -> R1 | J87: =OFFSET(Abilities!$N$1,MATCH(B87,Abilities!C:C,0)-1,-7) -> Affinity req | K87: =OFFSET(Abilities!$N$1,MATCH(B87,Abilities!C:C,0)-1,-12) -> Category | L87: =OFFSET(Abilities!$N$1,MATCH(B87,Abilities!C:C,0)-1,-9) -> Rules Text
A88: 1 | B88: Ability Name | G88: =IFERROR(OFFSET(Abilities!$N$1,MATCH(B88,Abilities!C:C,0)-1,A88),0) -> R1 | J88: =OFFSET(Abilities!$N$1,MATCH(B88,Abilities!C:C,0)-1,-7) -> Affinity req | K88: =OFFSET(Abilities!$N$1,MATCH(B88,Abilities!C:C,0)-1,-12) -> Category | L88: =OFFSET(Abilities!$N$1,MATCH(B88,Abilities!C:C,0)-1,-9) -> Rules Text
A89: 1 | B89: Ability Name | G89: =IFERROR(OFFSET(Abilities!$N$1,MATCH(B89,Abilities!C:C,0)-1,A89),0) -> R1 | J89: =OFFSET(Abilities!$N$1,MATCH(B89,Abilities!C:C,0)-1,-7) -> Affinity req | K89: =OFFSET(Abilities!$N$1,MATCH(B89,Abilities!C:C,0)-1,-12) -> Category | L89: =OFFSET(Abilities!$N$1,MATCH(B89,Abilities!C:C,0)-1,-9) -> Rules Text
A90: 1 | B90: Ability Name | G90: =IFERROR(OFFSET(Abilities!$N$1,MATCH(B90,Abilities!C:C,0)-1,A90),0) -> R1 | J90: =OFFSET(Abilities!$N$1,MATCH(B90,Abilities!C:C,0)-1,-7) -> Affinity req | K90: =OFFSET(Abilities!$N$1,MATCH(B90,Abilities!C:C,0)-1,-12) -> Category | L90: =OFFSET(Abilities!$N$1,MATCH(B90,Abilities!C:C,0)-1,-9) -> Rules Text
A91: 1 | B91: Ability Name | G91: =IFERROR(OFFSET(Abilities!$N$1,MATCH(B91,Abilities!C:C,0)-1,A91),0) -> R1 | J91: =OFFSET(Abilities!$N$1,MATCH(B91,Abilities!C:C,0)-1,-7) -> Affinity req | K91: =OFFSET(Abilities!$N$1,MATCH(B91,Abilities!C:C,0)-1,-12) -> Category | L91: =OFFSET(Abilities!$N$1,MATCH(B91,Abilities!C:C,0)-1,-9) -> Rules Text
A92: 1 | B92: Ability Name | G92: =IFERROR(OFFSET(Abilities!$N$1,MATCH(B92,Abilities!C:C,0)-1,A92),0) -> R1 | J92: =OFFSET(Abilities!$N$1,MATCH(B92,Abilities!C:C,0)-1,-7) -> Affinity req | K92: =OFFSET(Abilities!$N$1,MATCH(B92,Abilities!C:C,0)-1,-12) -> Category | L92: =OFFSET(Abilities!$N$1,MATCH(B92,Abilities!C:C,0)-1,-9) -> Rules Text
A93: 1 | B93: Ability Name | G93: =IFERROR(OFFSET(Abilities!$N$1,MATCH(B93,Abilities!C:C,0)-1,A93),0) -> R1 | J93: =OFFSET(Abilities!$N$1,MATCH(B93,Abilities!C:C,0)-1,-7) -> Affinity req | K93: =OFFSET(Abilities!$N$1,MATCH(B93,Abilities!C:C,0)-1,-12) -> Category | L93: =OFFSET(Abilities!$N$1,MATCH(B93,Abilities!C:C,0)-1,-9) -> Rules Text
A94: 1 | B94: Ability Name | G94: =IFERROR(OFFSET(Abilities!$N$1,MATCH(B94,Abilities!C:C,0)-1,A94),0) -> R1 | J94: =OFFSET(Abilities!$N$1,MATCH(B94,Abilities!C:C,0)-1,-7) -> Affinity req | K94: =OFFSET(Abilities!$N$1,MATCH(B94,Abilities!C:C,0)-1,-12) -> Category | L94: =OFFSET(Abilities!$N$1,MATCH(B94,Abilities!C:C,0)-1,-9) -> Rules Text
A95: 1 | B95: Ability Name | G95: =IFERROR(OFFSET(Abilities!$N$1,MATCH(B95,Abilities!C:C,0)-1,A95),0) -> R1 | J95: =OFFSET(Abilities!$N$1,MATCH(B95,Abilities!C:C,0)-1,-7) -> Affinity req | K95: =OFFSET(Abilities!$N$1,MATCH(B95,Abilities!C:C,0)-1,-12) -> Category | L95: =OFFSET(Abilities!$N$1,MATCH(B95,Abilities!C:C,0)-1,-9) -> Rules Text
A96: 1 | B96: Ability Name | G96: =IFERROR(OFFSET(Abilities!$N$1,MATCH(B96,Abilities!C:C,0)-1,A96),0) -> R1 | J96: =OFFSET(Abilities!$N$1,MATCH(B96,Abilities!C:C,0)-1,-7) -> Affinity req | K96: =OFFSET(Abilities!$N$1,MATCH(B96,Abilities!C:C,0)-1,-12) -> Category | L96: =OFFSET(Abilities!$N$1,MATCH(B96,Abilities!C:C,0)-1,-9) -> Rules Text
A97: 1 | B97: Ability Name | G97: =IFERROR(OFFSET(Abilities!$N$1,MATCH(B97,Abilities!C:C,0)-1,A97),0) -> R1 | J97: =OFFSET(Abilities!$N$1,MATCH(B97,Abilities!C:C,0)-1,-7) -> Affinity req | K97: =OFFSET(Abilities!$N$1,MATCH(B97,Abilities!C:C,0)-1,-12) -> Category | L97: =OFFSET(Abilities!$N$1,MATCH(B97,Abilities!C:C,0)-1,-9) -> Rules Text
A98: 1 | B98: Ability Name | G98: =IFERROR(OFFSET(Abilities!$N$1,MATCH(B98,Abilities!C:C,0)-1,A98),0) -> R1 | J98: =OFFSET(Abilities!$N$1,MATCH(B98,Abilities!C:C,0)-1,-7) -> Affinity req | K98: =OFFSET(Abilities!$N$1,MATCH(B98,Abilities!C:C,0)-1,-12) -> Category | L98: =OFFSET(Abilities!$N$1,MATCH(B98,Abilities!C:C,0)-1,-9) -> Rules Text
... A125: 1 | B125: Ability Name | G125: =IFERROR(OFFSET(Abilities!$N$1,MATCH(B125,Abilities!C:C,0)-1,A125),0) -> R1 | J125: =OFFSET(Abilities!$N$1,MATCH(B125,Abilities!C:C,0)-1,-7) -> Affinity req | K125: =OFFSET(Abilities!$N$1,MATCH(B125,Abilities!C:C,0)-1,-12) -> Category | L125: =OFFSET(Abilities!$N$1,MATCH(B125,Abilities!C:C,0)-1,-9) -> Rules Text
